<?xml version="1.0" encoding="utf-8"?>
<Cube method="Add" name="УФК_Свод ФУ" ClassType="9" SubClassType="0" Description="Классификатор районов, поступающий от УФК вместе с данными свода ФУ." DataSource="dv" OlapMode="0" DefaultMeasure="" AggregationPrefix="" EstimatedRows="837775" IsVisible="true" ProcessOptimizationMode="0" ProcessingKeyErrorLimit="0" AllowDrillThrough="false" FactTableSize="837775">
  <property name="SourceTable"><![CDATA["DV"."F_F_BUDGETINCOMINGSTULA"]]></property>
  <property name="SourceTableAlias"><![CDATA["DV"."F_F_BUDGETINCOMINGSTULA"]]></property>
  <property name="SourceTableFilter"><![CDATA[]]></property>
  <property name="Where"><![CDATA[]]></property>
  <property name="FromClause"><![CDATA["DV"."F_F_BUDGETINCOMINGSTULA", "DV"."DV_KD_UFK2", "DV"."DV_OKATO_UFK2", "DV"."BV_OKATO_BRIDGE", "DV"."DV_REGIONS_UFK2", "DV"."BV_REGIONS_BRIDGE", "DV"."FX_FX_BUDGETLEVELS", "DV"."DATASOURCES", "DV"."BV_KD_BRIDGE", "DV"."BV_KD_BRIDGEPLAN", "DV"."BV_REGIONS_BRIDGEPLAN", "DV"."BV_KIF_BRIDGEPLAN", "DV"."BV_KIF_BRIDGE", "DV"."BV_KVSR_BRIDGE", "DV"."BV_PROGRAMS_BRIDGE", "DV"."D_DOC_LIST", "DV"."DV_FX_DATE_YEARDAYUNV", "DV"."FX_DATE_YEARDAYUNV"]]></property>
  <property name="JoinClause"><![CDATA[("DV"."F_F_BUDGETINCOMINGSTULA"."REFKD"="DV"."DV_KD_UFK2"."ID") AND ("DV"."F_F_BUDGETINCOMINGSTULA"."REFOKATO"="DV"."DV_OKATO_UFK2"."ID") AND ("DV"."DV_OKATO_UFK2"."REFBRIDGEOKATO"="DV"."BV_OKATO_BRIDGE"."ID") AND ("DV"."F_F_BUDGETINCOMINGSTULA"."REFREGIONS"="DV"."DV_REGIONS_UFK2"."ID") AND ("DV"."DV_REGIONS_UFK2"."REFBRIDGEREGIONS"="DV"."BV_REGIONS_BRIDGE"."ID") AND ("DV"."F_F_BUDGETINCOMINGSTULA"."REFBUDGETLEVELS"="DV"."FX_FX_BUDGETLEVELS"."ID") AND ("DV"."F_F_BUDGETINCOMINGSTULA"."SOURCEID"="DV"."DATASOURCES"."ID") AND ("DV"."DV_KD_UFK2"."REFBRIDGEKD"="DV"."BV_KD_BRIDGE"."ID") AND ("DV"."DV_KD_UFK2"."REFBRIDGEKDPLAN"="DV"."BV_KD_BRIDGEPLAN"."ID") AND ("DV"."DV_REGIONS_UFK2"."REFBRIDGEREGIONSPLAN"="DV"."BV_REGIONS_BRIDGEPLAN"."ID") AND ("DV"."DV_KD_UFK2"."REFKIFBRIDGEPLAN"="DV"."BV_KIF_BRIDGEPLAN"."ID") AND ("DV"."DV_KD_UFK2"."REFKIFBRIDGE"="DV"."BV_KIF_BRIDGE"."ID") AND ("DV"."DV_KD_UFK2"."REFKVSRBRIDGE"="DV"."BV_KVSR_BRIDGE"."ID") AND ("DV"."DV_KD_UFK2"."REFPROGRAMSBRIDGE"="DV"."BV_PROGRAMS_BRIDGE"."ID") AND ("DV"."F_F_BUDGETINCOMINGSTULA"."REFDOC"="DV"."D_DOC_LIST"."ID") AND ("DV"."F_F_BUDGETINCOMINGSTULA"."REFFKDAY"="DV"."DV_FX_DATE_YEARDAYUNV"."ID") AND ("DV"."F_F_BUDGETINCOMINGSTULA"."REFYEARDAYUNV"="DV"."FX_DATE_YEARDAYUNV"."ID")]]></property>
  <property name="ProcessingKeyErrorLogFileName"><![CDATA[]]></property>
  <property name="DrillThroughColumns"><![CDATA[]]></property>
  <property name="DrillThroughFrom"><![CDATA[]]></property>
  <property name="DrillThroughJoins"><![CDATA[]]></property>
  <property name="DrillThroughFilter"><![CDATA[]]></property>
  <property name="FactTable"><![CDATA["DV"."F_F_BUDGETINCOMINGSTULA"]]></property>
  <CustomProperties>
    <Property name="SchemaLayout" datatype="0"><![CDATA[({dv}{DV.DV_KD_UFK2}{DV.DV_KD_UFK2}{1704}{6396}{1800}{4078}{1})({dv}{DV.BV_OKATO_BRIDGE}{DV.BV_OKATO_BRIDGE}{6216}{6708}{1839}{940}{1})({dv}{DV.DV_OKATO_UFK2}{DV.DV_OKATO_UFK2}{4451}{4120}{1800}{970}{1})({dv}{DV.BV_REGIONS_BRIDGE}{DV.BV_REGIONS_BRIDGE}{7416}{6480}{2163}{910}{1})({dv}{DV.DV_REGIONS_UFK2}{DV.DV_REGIONS_UFK2}{6648}{3696}{1932}{2368}{1})({dv}{DV.FX_FX_BUDGETLEVELS}{DV.FX_FX_BUDGETLEVELS}{72}{3480}{2214}{1417}{1})({dv}{DV.F_F_BUDGETINCOMINGSTULA}{DV.F_F_BUDGETINCOMINGSTULA}{2659}{11}{2727}{4037}{1})({dv}{DV.DATASOURCES}{DV.DATASOURCES}{300}{576}{1800}{1105}{1})({dv}{DV.BV_KD_BRIDGE}{DV.BV_KD_BRIDGE}{1140}{9096}{1800}{988}{1})({dv}{DV.BV_KD_BRIDGEPLAN}{DV.BV_KD_BRIDGEPLAN}{5676}{9072}{1947}{916}{1})({dv}{DV.BV_REGIONS_BRIDGEPLAN}{DV.BV_REGIONS_BRIDGEPLAN}{8580}{6672}{2331}{910}{1})({dv}{DV.BV_KIF_BRIDGE}{DV.BV_KIF_BRIDGE}{4608}{9192}{1800}{904}{1})({dv}{DV.BV_KIF_BRIDGEPLAN}{DV.BV_KIF_BRIDGEPLAN}{6792}{9192}{2016}{904}{1})({dv}{DV.BV_KVSR_BRIDGE}{DV.BV_KVSR_BRIDGE}{2328}{9288}{1800}{928}{1})({dv}{DV.BV_PROGRAMS_BRIDGE}{DV.BV_PROGRAMS_BRIDGE}{3492}{9036}{2184}{916}{1})({dv}{DV.D_DOC_LIST}{DV.D_DOC_LIST}{6945}{930}{1965}{910}{1})({dv}{DV.DV_FX_DATE_YEARDAYUNV}{DV.DV_FX_DATE_YEARDAYUNV}{8940}{1605}{2820}{910}{1})({dv}{DV.FX_DATE_YEARDAYUNV}{DV.FX_DATE_YEARDAYUNV}{10320}{1575}{2565}{910}{1})]]></Property>
    <Property name="FullName" datatype="8"><![CDATA[f.F.BudgetIncomingsTula]]></Property>
    <Property name="SchemaJoins" datatype="0"><![CDATA[("DV"."F_F_BUDGETINCOMINGSTULA"."REFKD"="DV"."DV_KD_UFK2"."ID") AND ("DV"."F_F_BUDGETINCOMINGSTULA"."REFOKATO"="DV"."DV_OKATO_UFK2"."ID") AND ("DV"."DV_OKATO_UFK2"."REFBRIDGEOKATO"="DV"."BV_OKATO_BRIDGE"."ID") AND ("DV"."F_F_BUDGETINCOMINGSTULA"."REFREGIONS"="DV"."DV_REGIONS_UFK2"."ID") AND ("DV"."DV_REGIONS_UFK2"."REFBRIDGEREGIONS"="DV"."BV_REGIONS_BRIDGE"."ID") AND ("DV"."F_F_BUDGETINCOMINGSTULA"."REFBUDGETLEVELS"="DV"."FX_FX_BUDGETLEVELS"."ID") AND ("DV"."F_F_BUDGETINCOMINGSTULA"."SOURCEID"="DV"."DATASOURCES"."ID") AND ("DV"."DV_KD_UFK2"."REFBRIDGEKD"="DV"."BV_KD_BRIDGE"."ID") AND ("DV"."DV_KD_UFK2"."REFBRIDGEKDPLAN"="DV"."BV_KD_BRIDGEPLAN"."ID") AND ("DV"."DV_REGIONS_UFK2"."REFBRIDGEREGIONSPLAN"="DV"."BV_REGIONS_BRIDGEPLAN"."ID") AND ("DV"."DV_KD_UFK2"."REFKIFBRIDGEPLAN"="DV"."BV_KIF_BRIDGEPLAN"."ID") AND ("DV"."DV_KD_UFK2"."REFKIFBRIDGE"="DV"."BV_KIF_BRIDGE"."ID") AND ("DV"."DV_KD_UFK2"."REFKVSRBRIDGE"="DV"."BV_KVSR_BRIDGE"."ID") AND ("DV"."DV_KD_UFK2"."REFPROGRAMSBRIDGE"="DV"."BV_PROGRAMS_BRIDGE"."ID") AND ("DV"."F_F_BUDGETINCOMINGSTULA"."REFDOC"="DV"."D_DOC_LIST"."ID") AND ("DV"."F_F_BUDGETINCOMINGSTULA"."REFFKDAY"="DV"."DV_FX_DATE_YEARDAYUNV"."ID") AND ("DV"."F_F_BUDGETINCOMINGSTULA"."REFYEARDAYUNV"="DV"."FX_DATE_YEARDAYUNV"."ID")]]></Property>
    <Property name="SubClass" datatype="8"><![CDATA[ИМПОРТ]]></Property>
    <Property name="ID" datatype="8"><![CDATA[fe61cccf-4b5f-4162-a2bb-1e440167c4d7]]></Property>
    <Property name="MeasureGroupID" datatype="8"><![CDATA[38d08d96-1e19-402f-81b9-0dc671492249]]></Property>
    <Property name="ObjectKey" datatype="8"><![CDATA[826d5da9-c9cc-4f8d-9432-d7357fda4677]]></Property>
  </CustomProperties>
  <DataSources>
    <DataSource method="Add" name="dv" ClassType="6" SubClassType="0">
      <CustomProperties>
        <Property name="ID" datatype="8"><![CDATA[af4c64e8-2b41-4fab-a1fa-acd52b27625e]]></Property>
      </CustomProperties>
    </DataSource>
  </DataSources>
  <CubeDimensions>
    <CubeDimension method="Add" name="ОКАТО.Сопоставимый" ClassType="11" SubClassType="2" AggregationUsage="0" IsVisible="true" Num="1">
      <CubeLevels>
        <CubeLevel method="Update" name="(All)" ClassType="12" SubClassType="0" EnableAggregations="true" IsDisabled="false" IsVisible="true">
          <property name="CustomRollUpExpression"><![CDATA[]]></property>
          <property name="MemberKeyColumn"><![CDATA[Все коды ОКАТО]]></property>
        </CubeLevel>
        <CubeLevel method="Update" name="Код ОКАТО" ClassType="12" SubClassType="2" EnableAggregations="true" IsVisible="true">
          <property name="CustomRollUpExpression"><![CDATA[]]></property>
          <property name="MemberKeyColumn"><![CDATA["DV"."BV_OKATO_BRIDGE"."ID"]]></property>
        </CubeLevel>
      </CubeLevels>
    </CubeDimension>
    <CubeDimension method="Add" name="ОКАТО.УФК_Свод ФУ" ClassType="11" SubClassType="0" AggregationUsage="0" IsVisible="true" Num="2">
      <CubeLevels>
        <CubeLevel method="Update" name="(All)" ClassType="12" SubClassType="0" EnableAggregations="true" IsDisabled="false" IsVisible="true">
          <property name="CustomRollUpExpression"><![CDATA[]]></property>
          <property name="MemberKeyColumn"><![CDATA[Данные всех источников]]></property>
        </CubeLevel>
        <CubeLevel method="Update" name="Источник" ClassType="12" SubClassType="0" EnableAggregations="true" IsDisabled="false" IsVisible="true">
          <property name="CustomRollUpExpression"><![CDATA[]]></property>
          <property name="MemberKeyColumn"><![CDATA["DV"."DV_OKATO_UFK2"."SOURCEID"]]></property>
        </CubeLevel>
        <CubeLevel method="Update" name="Код ОКАТО" ClassType="12" SubClassType="0" EnableAggregations="true" IsDisabled="false" IsVisible="true">
          <property name="CustomRollUpExpression"><![CDATA[]]></property>
          <property name="MemberKeyColumn"><![CDATA["DV"."DV_OKATO_UFK2"."CODE"]]></property>
        </CubeLevel>
      </CubeLevels>
    </CubeDimension>
    <CubeDimension method="Add" name="Уровни бюджетов" ClassType="11" SubClassType="2" AggregationUsage="0" IsVisible="true" Num="3">
      <CubeLevels>
        <CubeLevel method="Update" name="(All)" ClassType="12" SubClassType="0" EnableAggregations="true" IsDisabled="false" IsVisible="true">
          <property name="CustomRollUpExpression"><![CDATA[]]></property>
          <property name="MemberKeyColumn"><![CDATA[Все]]></property>
        </CubeLevel>
        <CubeLevel method="Update" name="Уровень бюджета" ClassType="12" SubClassType="2" EnableAggregations="true" IsVisible="true">
          <property name="CustomRollUpExpression"><![CDATA[CalculationPassValue(
  IIF(not isEmpty([Уровни бюджетов].CurrentMember.DataMember),
    [Уровни бюджетов].CurrentMember.DataMember,
    CalculationPassValue(Sum(descendants([Уровни бюджетов].CurrentMember, 1), [Measures].CurrentMember), 1)
)
,
0)

]]></property>
          <property name="MemberKeyColumn"><![CDATA["DV"."FX_FX_BUDGETLEVELS"."ID"]]></property>
        </CubeLevel>
      </CubeLevels>
    </CubeDimension>
    <CubeDimension method="Add" name="Источники данных" ClassType="11" SubClassType="0" AggregationUsage="0" IsVisible="true" Num="4">
      <CubeLevels>
        <CubeLevel method="Update" name="(All)" ClassType="12" SubClassType="0" EnableAggregations="true" IsDisabled="false" IsVisible="true">
          <property name="CustomRollUpExpression"><![CDATA[]]></property>
          <property name="MemberKeyColumn"><![CDATA[Все источники данных]]></property>
        </CubeLevel>
        <CubeLevel method="Update" name="Источник" ClassType="12" SubClassType="0" EnableAggregations="true" IsDisabled="false" IsVisible="true">
          <property name="CustomRollUpExpression"><![CDATA[]]></property>
          <property name="MemberKeyColumn"><![CDATA["DV"."DATASOURCES"."ID"]]></property>
        </CubeLevel>
      </CubeLevels>
    </CubeDimension>
    <CubeDimension method="Add" name="КД.Сопоставимый План" ClassType="11" SubClassType="2" AggregationUsage="0" IsVisible="true" Num="5">
      <CubeLevels>
        <CubeLevel method="Update" name="(All)" ClassType="12" SubClassType="0" EnableAggregations="true" IsDisabled="false" IsVisible="true">
          <property name="CustomRollUpExpression"><![CDATA[]]></property>
          <property name="MemberKeyColumn"><![CDATA[Все коды доходов]]></property>
        </CubeLevel>
        <CubeLevel method="Update" name="Код дохода" ClassType="12" SubClassType="2" EnableAggregations="true" IsVisible="true">
          <property name="CustomRollUpExpression"><![CDATA[]]></property>
          <property name="MemberKeyColumn"><![CDATA["DV"."BV_KD_BRIDGEPLAN"."ID"]]></property>
        </CubeLevel>
      </CubeLevels>
    </CubeDimension>
    <CubeDimension method="Add" name="КД.Сопоставимый" ClassType="11" SubClassType="2" AggregationUsage="0" IsVisible="true" Num="6">
      <CubeLevels>
        <CubeLevel method="Update" name="(All)" ClassType="12" SubClassType="0" EnableAggregations="true" IsDisabled="false" IsVisible="true">
          <property name="CustomRollUpExpression"><![CDATA[]]></property>
          <property name="MemberKeyColumn"><![CDATA[Все коды доходов]]></property>
        </CubeLevel>
        <CubeLevel method="Update" name="Код дохода" ClassType="12" SubClassType="2" EnableAggregations="true" IsVisible="true">
          <property name="CustomRollUpExpression"><![CDATA[]]></property>
          <property name="MemberKeyColumn"><![CDATA["DV"."BV_KD_BRIDGE"."ID"]]></property>
        </CubeLevel>
      </CubeLevels>
    </CubeDimension>
    <CubeDimension method="Add" name="КД.УФК_Свод ФУ" ClassType="11" SubClassType="0" AggregationUsage="0" IsVisible="true" Num="7">
      <CubeLevels>
        <CubeLevel method="Update" name="(All)" ClassType="12" SubClassType="0" EnableAggregations="true" IsDisabled="false" IsVisible="true">
          <property name="CustomRollUpExpression"><![CDATA[]]></property>
          <property name="MemberKeyColumn"><![CDATA[Данные всех источников]]></property>
        </CubeLevel>
        <CubeLevel method="Update" name="Источник" ClassType="12" SubClassType="0" EnableAggregations="true" IsDisabled="false" IsVisible="true">
          <property name="CustomRollUpExpression"><![CDATA[]]></property>
          <property name="MemberKeyColumn"><![CDATA["DV"."DV_KD_UFK2"."SOURCEID"]]></property>
        </CubeLevel>
        <CubeLevel method="Update" name="Код дохода" ClassType="12" SubClassType="0" EnableAggregations="true" IsDisabled="false" IsVisible="true">
          <property name="CustomRollUpExpression"><![CDATA[]]></property>
          <property name="MemberKeyColumn"><![CDATA["DV"."DV_KD_UFK2"."CODESTR"]]></property>
        </CubeLevel>
      </CubeLevels>
    </CubeDimension>
    <CubeDimension method="Add" name="КИФ.Сопоставимый" ClassType="11" SubClassType="2" AggregationUsage="0" IsVisible="true" Num="8">
      <CubeLevels>
        <CubeLevel method="Update" name="(All)" ClassType="12" SubClassType="0" EnableAggregations="true" IsDisabled="false" IsVisible="true">
          <property name="CustomRollUpExpression"><![CDATA[]]></property>
          <property name="MemberKeyColumn"><![CDATA[Все источники финансирования]]></property>
        </CubeLevel>
        <CubeLevel method="Update" name="Источники финансирования" ClassType="12" SubClassType="2" EnableAggregations="true" IsVisible="true">
          <property name="CustomRollUpExpression"><![CDATA[]]></property>
          <property name="MemberKeyColumn"><![CDATA["DV"."BV_KIF_BRIDGE"."ID"]]></property>
        </CubeLevel>
      </CubeLevels>
    </CubeDimension>
    <CubeDimension method="Add" name="КИФ.Сопоставимый планирование" ClassType="11" SubClassType="2" AggregationUsage="0" IsVisible="true" Num="9">
      <CubeLevels>
        <CubeLevel method="Update" name="(All)" ClassType="12" SubClassType="0" EnableAggregations="true" IsDisabled="false" IsVisible="true">
          <property name="CustomRollUpExpression"><![CDATA[]]></property>
          <property name="MemberKeyColumn"><![CDATA[Все источники финансирования]]></property>
        </CubeLevel>
        <CubeLevel method="Update" name="Источник финансирования" ClassType="12" SubClassType="2" EnableAggregations="true" IsVisible="true">
          <property name="CustomRollUpExpression"><![CDATA[]]></property>
          <property name="MemberKeyColumn"><![CDATA["DV"."BV_KIF_BRIDGEPLAN"."ID"]]></property>
        </CubeLevel>
      </CubeLevels>
    </CubeDimension>
    <CubeDimension method="Add" name="Администратор.Сопоставим" ClassType="11" SubClassType="0" AggregationUsage="0" IsVisible="true" Num="10">
      <CubeLevels>
        <CubeLevel method="Update" name="(All)" ClassType="12" SubClassType="0" EnableAggregations="true" IsDisabled="false" IsVisible="true">
          <property name="CustomRollUpExpression"><![CDATA[]]></property>
          <property name="MemberKeyColumn"><![CDATA[Все администраторы]]></property>
        </CubeLevel>
        <CubeLevel method="Update" name="Администратор" ClassType="12" SubClassType="0" EnableAggregations="true" IsDisabled="false" IsVisible="true">
          <property name="CustomRollUpExpression"><![CDATA[]]></property>
          <property name="MemberKeyColumn"><![CDATA["DV"."BV_KVSR_BRIDGE"."ID"]]></property>
        </CubeLevel>
      </CubeLevels>
    </CubeDimension>
    <CubeDimension method="Add" name="Районы.Сопоставимый" ClassType="11" SubClassType="2" AggregationUsage="0" IsVisible="true" Num="11">
      <CubeLevels>
        <CubeLevel method="Update" name="(All)" ClassType="12" SubClassType="0" EnableAggregations="true" IsDisabled="false" IsVisible="true">
          <property name="CustomRollUpExpression"><![CDATA[]]></property>
          <property name="MemberKeyColumn"><![CDATA[Все районы]]></property>
        </CubeLevel>
        <CubeLevel method="Update" name="Район" ClassType="12" SubClassType="2" EnableAggregations="true" IsVisible="true">
          <property name="CustomRollUpExpression"><![CDATA[]]></property>
          <property name="MemberKeyColumn"><![CDATA["DV"."BV_REGIONS_BRIDGE"."ID"]]></property>
        </CubeLevel>
      </CubeLevels>
    </CubeDimension>
    <CubeDimension method="Add" name="Районы.Сопоставимый План" ClassType="11" SubClassType="2" AggregationUsage="0" IsVisible="true" Num="12">
      <CubeLevels>
        <CubeLevel method="Update" name="(All)" ClassType="12" SubClassType="0" EnableAggregations="true" IsDisabled="false" IsVisible="true">
          <property name="CustomRollUpExpression"><![CDATA[]]></property>
          <property name="MemberKeyColumn"><![CDATA[Все районы]]></property>
        </CubeLevel>
        <CubeLevel method="Update" name="Район" ClassType="12" SubClassType="2" EnableAggregations="true" IsVisible="true">
          <property name="CustomRollUpExpression"><![CDATA[]]></property>
          <property name="MemberKeyColumn"><![CDATA["DV"."BV_REGIONS_BRIDGEPLAN"."ID"]]></property>
        </CubeLevel>
      </CubeLevels>
    </CubeDimension>
    <CubeDimension method="Add" name="Районы.УФК_Свод ФУ" ClassType="11" SubClassType="0" AggregationUsage="0" IsVisible="true" Num="13">
      <CubeLevels>
        <CubeLevel method="Update" name="(All)" ClassType="12" SubClassType="0" EnableAggregations="true" IsDisabled="false" IsVisible="true">
          <property name="CustomRollUpExpression"><![CDATA[]]></property>
          <property name="MemberKeyColumn"><![CDATA[Данные всех источников]]></property>
        </CubeLevel>
        <CubeLevel method="Update" name="Источник" ClassType="12" SubClassType="0" EnableAggregations="true" IsDisabled="false" IsVisible="true">
          <property name="CustomRollUpExpression"><![CDATA[]]></property>
          <property name="MemberKeyColumn"><![CDATA["DV"."DV_REGIONS_UFK2"."SOURCEID"]]></property>
        </CubeLevel>
        <CubeLevel method="Update" name="Район" ClassType="12" SubClassType="0" EnableAggregations="true" IsDisabled="false" IsVisible="true">
          <property name="CustomRollUpExpression"><![CDATA[]]></property>
          <property name="MemberKeyColumn"><![CDATA["DV"."DV_REGIONS_UFK2"."ID"]]></property>
        </CubeLevel>
      </CubeLevels>
    </CubeDimension>
    <CubeDimension method="Add" name="Программы.Сопоставимый" ClassType="11" SubClassType="0" AggregationUsage="0" IsVisible="true" Num="14">
      <CubeLevels>
        <CubeLevel method="Update" name="(All)" ClassType="12" SubClassType="0" EnableAggregations="true" IsDisabled="false" IsVisible="true">
          <property name="CustomRollUpExpression"><![CDATA[]]></property>
          <property name="MemberKeyColumn"><![CDATA[Все программы]]></property>
        </CubeLevel>
        <CubeLevel method="Update" name="Программа" ClassType="12" SubClassType="0" EnableAggregations="true" IsDisabled="false" IsVisible="true">
          <property name="CustomRollUpExpression"><![CDATA[]]></property>
          <property name="MemberKeyColumn"><![CDATA["DV"."BV_PROGRAMS_BRIDGE"."ID"]]></property>
        </CubeLevel>
      </CubeLevels>
    </CubeDimension>
    <CubeDimension method="Add" name="Документы.Ведомость Операция" ClassType="11" SubClassType="0" AggregationUsage="0" IsVisible="true" Num="15">
      <CubeLevels>
        <CubeLevel method="Update" name="(All)" ClassType="12" SubClassType="0" EnableAggregations="true" IsDisabled="false" IsVisible="true">
          <property name="CustomRollUpExpression"><![CDATA[]]></property>
          <property name="MemberKeyColumn"><![CDATA[Все]]></property>
        </CubeLevel>
        <CubeLevel method="Update" name="Ведомость" ClassType="12" SubClassType="0" EnableAggregations="true" IsDisabled="false" IsVisible="true">
          <property name="CustomRollUpExpression"><![CDATA[]]></property>
          <property name="MemberKeyColumn"><![CDATA["DV"."D_DOC_LIST"."ID"]]></property>
        </CubeLevel>
      </CubeLevels>
    </CubeDimension>
    <CubeDimension method="Add" name="Период.День ФК" ClassType="11" SubClassType="2" AggregationUsage="0" IsVisible="true" Num="16">
      <CubeLevels>
        <CubeLevel method="Update" name="(All)" ClassType="12" SubClassType="0" EnableAggregations="true" IsDisabled="false" IsVisible="true">
          <property name="CustomRollUpExpression"><![CDATA[]]></property>
          <property name="MemberKeyColumn"><![CDATA[Данные всех периодов]]></property>
        </CubeLevel>
        <CubeLevel method="Update" name="Период" ClassType="12" SubClassType="2" EnableAggregations="true" IsVisible="true">
          <property name="CustomRollUpExpression"><![CDATA[/*CalculationPassValue(
  IIF(isEmpty([Период].[День ФК].CurrentMember.DataMember),
    [Период].[День ФК].CurrentMember,
    [Период].[День ФК].CurrentMember.DataMember),
0)
*/]]></property>
          <property name="MemberKeyColumn"><![CDATA["DV"."DV_FX_DATE_YEARDAYUNV"."ID"]]></property>
        </CubeLevel>
      </CubeLevels>
    </CubeDimension>
    <CubeDimension method="Add" name="Период.Период" ClassType="11" SubClassType="0" AggregationUsage="0" IsVisible="true" Num="17">
      <CubeLevels>
        <CubeLevel method="Update" name="(All)" ClassType="12" SubClassType="0" EnableAggregations="true" IsDisabled="false" IsVisible="true">
          <property name="CustomRollUpExpression"><![CDATA[]]></property>
          <property name="MemberKeyColumn"><![CDATA[Данные всех периодов]]></property>
        </CubeLevel>
        <CubeLevel method="Update" name="Год" ClassType="12" SubClassType="0" EnableAggregations="true" IsDisabled="false" IsVisible="true">
          <property name="CustomRollUpExpression"><![CDATA[]]></property>
          <property name="MemberKeyColumn"><![CDATA["DV"."FX_DATE_YEARDAYUNV"."DATEYEARID"]]></property>
        </CubeLevel>
        <CubeLevel method="Update" name="Полугодие" ClassType="12" SubClassType="0" EnableAggregations="true" IsDisabled="false" IsVisible="true">
          <property name="CustomRollUpExpression"><![CDATA[]]></property>
          <property name="MemberKeyColumn"><![CDATA["DV"."FX_DATE_YEARDAYUNV"."DATEHALFYEARID"]]></property>
        </CubeLevel>
        <CubeLevel method="Update" name="Квартал" ClassType="12" SubClassType="0" EnableAggregations="true" IsDisabled="false" IsVisible="true">
          <property name="CustomRollUpExpression"><![CDATA[]]></property>
          <property name="MemberKeyColumn"><![CDATA["DV"."FX_DATE_YEARDAYUNV"."DATEQUARTERID"]]></property>
        </CubeLevel>
        <CubeLevel method="Update" name="Месяц" ClassType="12" SubClassType="0" EnableAggregations="true" IsDisabled="false" IsVisible="true">
          <property name="CustomRollUpExpression"><![CDATA[]]></property>
          <property name="MemberKeyColumn"><![CDATA["DV"."FX_DATE_YEARDAYUNV"."DATEMONTHID"]]></property>
        </CubeLevel>
        <CubeLevel method="Update" name="День" ClassType="12" SubClassType="0" EnableAggregations="true" IsDisabled="false" IsVisible="true">
          <property name="CustomRollUpExpression"><![CDATA[]]></property>
          <property name="MemberKeyColumn"><![CDATA["DV"."FX_DATE_YEARDAYUNV"."ID"]]></property>
        </CubeLevel>
      </CubeLevels>
    </CubeDimension>
  </CubeDimensions>
  <CubeMeasures>
    <CubeMeasure method="Add" name="Сумма" ClassType="10" SubClassType="0" Description="" IsVisible="true" SourceColumnType="5" AggregateFunction="0" FormatString="Currency" Num="1">
      <property name="SourceColumn"><![CDATA["DV"."F_F_BUDGETINCOMINGSTULA"."SUMME"]]></property>
    </CubeMeasure>
    <CubeMeasure method="Add" name="Сумма с начала года" ClassType="10" SubClassType="0" Description="" IsVisible="false" SourceColumnType="5" AggregateFunction="0" FormatString="Currency" Num="2">
      <property name="SourceColumn"><![CDATA["DV"."F_F_BUDGETINCOMINGSTULA"."FROMBEGINYEAR"]]></property>
    </CubeMeasure>
  </CubeMeasures>
  <CubeRoles />
  <CubeCommands>
    <CubeCommand method="Add" name="Сумма нарастающим итогом" ClassType="13" SubClassType="0" Description="" CommandType="1">
      <property name="Statement"><![CDATA[CREATE MEMBER CURRENTCUBE.Measures.[Сумма нарастающим итогом] AS '/*CalculationPassValue(*/
IIF(
/*[Период].[Период].CurrentMember.Level is [Период].[Период].[(All)] or
[Период].[Период].CurrentMember.Level is [Период].[Период].[Год] or
([Период].[Период].CurrentMember Is OpeningPeriod([Период].[Период].CurrentMember.Level, Ancestor([Период].[Период].CurrentMember, [Период].[Период].[Год]))),
(Measures.[Сумма], [Период].[Период].CurrentMember),
*/
IsLeaf([Период].[Период].CurrentMember),
Sum({OpeningPeriod([Период].[Период].CurrentMember.Level, Ancestor([Период].[Период].CurrentMember, [Период].[Период].[Год])):
[Период].[Период].CurrentMember}, Measures.[Сумма]),
IIF([Период].[Период].CurrentMember.Level is [Период].[Период].[(All)] ,  CalculationPassValue(Sum([Период].[Период].CurrentMember.Children, [Measures].[Сумма нарастающим итогом]), 1),
 CalculationPassValue(([Период].[Период].CurrentMember.LastChild, [Measures].[Сумма нарастающим итогом]), 1)))

/*CalculationPassValue(Tail(Filter([Период].[Период].CurrentMember.Children, not IsEmpty([Measures].[Сумма нарастающим итогом]) and ([Measures].[Сумма нарастающим итогом])<> 0)).Item(0), 1))*/

/*, 0)*/']]></property>
    </CubeCommand>
    <CubeCommand method="Add" name="За аналогичный период прошлого года" ClassType="13" SubClassType="0" Description="" CommandType="1">
      <property name="Statement"><![CDATA[CREATE MEMBER CURRENTCUBE.Measures.[За аналогичный период прошлого года] AS '([Measures].[Сумма], ParallelPeriod([Период].[Период].[Год], 1, [Период].[Период].CurrentMember))', FORMAT_STRING = 'Currency']]></property>
    </CubeCommand>
    <CubeCommand method="Add" name="За аналогичный период прошлого года нараст итог" ClassType="13" SubClassType="0" Description="" CommandType="1">
      <property name="Statement"><![CDATA[CREATE MEMBER CURRENTCUBE.Measures.[За аналогичный период прошлого года нараст итог] AS '([Measures].[Сумма нарастающим итогом], ParallelPeriod([Период].[Период].[Год], 1, [Период].[Период].CurrentMember))']]></property>
    </CubeCommand>
    <CubeCommand method="Add" name="Темп роста к прошлому году" ClassType="13" SubClassType="0" Description="" CommandType="1">
      <property name="Statement"><![CDATA[CREATE MEMBER CURRENTCUBE.Measures.[Темп роста к прошлому году] AS 'IIF(IsEmpty([Measures].[За аналогичный период прошлого года]) or [Measures].[За аналогичный период прошлого года] = 0,
	null,
	Measures.[Сумма]/Measures.[За аналогичный период прошлого года]
)', FORMAT_STRING = 'Percent']]></property>
    </CubeCommand>
    <CubeCommand method="Add" name="Темп роста к прошлому периоду" ClassType="13" SubClassType="0" Description="" CommandType="1">
      <property name="Statement"><![CDATA[CREATE MEMBER CURRENTCUBE.Measures.[Темп роста к прошлому периоду] AS 'IIF(Isempty(([Measures].[Сумма], [Период].[Период].CurrentMember)), null,

IIF((not IsEmpty(([Measures].[Сумма], [Период].[Период].lag(1))) and ([Measures].[Сумма], [Период].[Период].lag(1)) <>0) , ([Measures].[Сумма], [Период].[Период].CurrentMember)/([Measures].[Сумма], [Период].[Период].Lag(1)),
IIF((not IsEmpty(([Measures].[Сумма], [Период].[Период].lag(2))) and ([Measures].[Сумма], [Период].[Период].lag(2)) <>0) , ([Measures].[Сумма], [Период].[Период].CurrentMember)/([Measures].[Сумма], [Период].[Период].Lag(2)),
IIF((not IsEmpty(([Measures].[Сумма], [Период].[Период].lag(3))) and ([Measures].[Сумма], [Период].[Период].lag(3)) <>0) , ([Measures].[Сумма], [Период].[Период].CurrentMember)/([Measures].[Сумма], [Период].[Период].Lag(3)),
IIF((not IsEmpty(([Measures].[Сумма], [Период].[Период].lag(4))) and ([Measures].[Сумма], [Период].[Период].lag(4)) <>0) , ([Measures].[Сумма], [Период].[Период].CurrentMember)/([Measures].[Сумма], [Период].[Период].Lag(4)),
IIF((not IsEmpty(([Measures].[Сумма], [Период].[Период].lag(5))) and ([Measures].[Сумма], [Период].[Период].lag(5)) <>0) , ([Measures].[Сумма], [Период].[Период].CurrentMember)/([Measures].[Сумма], [Период].[Период].Lag(5)),
IIF((not IsEmpty(([Measures].[Сумма], [Период].[Период].lag(6))) and ([Measures].[Сумма], [Период].[Период].lag(6)) <>0) , ([Measures].[Сумма], [Период].[Период].CurrentMember)/([Measures].[Сумма], [Период].[Период].Lag(6)),
IIF((not IsEmpty(([Measures].[Сумма], [Период].[Период].lag(7))) and ([Measures].[Сумма], [Период].[Период].lag(7)) <>0) , ([Measures].[Сумма], [Период].[Период].CurrentMember)/([Measures].[Сумма], [Период].[Период].Lag(7)),
IIF((not IsEmpty(([Measures].[Сумма], [Период].[Период].lag(8))) and ([Measures].[Сумма], [Период].[Период].lag(8)) <>0) , ([Measures].[Сумма], [Период].[Период].CurrentMember)/([Measures].[Сумма], [Период].[Период].Lag(8)),
IIF((not IsEmpty(([Measures].[Сумма], [Период].[Период].lag(9))) and ([Measures].[Сумма], [Период].[Период].lag(9)) <>0) , ([Measures].[Сумма], [Период].[Период].CurrentMember)/([Measures].[Сумма], [Период].[Период].Lag(9)),
IIF((not IsEmpty(([Measures].[Сумма], [Период].[Период].lag(10))) and ([Measures].[Сумма], [Период].[Период].lag(10)) <>0) , ([Measures].[Сумма], [Период].[Период].CurrentMember)/([Measures].[Сумма], [Период].[Период].Lag(10)),
IIF((not IsEmpty(([Measures].[Сумма], [Период].[Период].lag(11))) and ([Measures].[Сумма], [Период].[Период].lag(11)) <>0) , ([Measures].[Сумма], [Период].[Период].CurrentMember)/([Measures].[Сумма], [Период].[Период].Lag(11)),
IIF((not IsEmpty(([Measures].[Сумма], [Период].[Период].lag(12))) and ([Measures].[Сумма], [Период].[Период].lag(12)) <>0) , ([Measures].[Сумма], [Период].[Период].CurrentMember)/([Measures].[Сумма], [Период].[Период].Lag(12)),
IIF((not IsEmpty(([Measures].[Сумма], [Период].[Период].lag(13))) and ([Measures].[Сумма], [Период].[Период].lag(13)) <>0) , ([Measures].[Сумма], [Период].[Период].CurrentMember)/([Measures].[Сумма], [Период].[Период].Lag(13)),
IIF((not IsEmpty(([Measures].[Сумма], [Период].[Период].lag(14))) and ([Measures].[Сумма], [Период].[Период].lag(14)) <>0) , ([Measures].[Сумма], [Период].[Период].CurrentMember)/([Measures].[Сумма], [Период].[Период].Lag(14)),
IIF((not IsEmpty(([Measures].[Сумма], [Период].[Период].lag(15))) and ([Measures].[Сумма], [Период].[Период].lag(15)) <>0) , ([Measures].[Сумма], [Период].[Период].CurrentMember)/([Measures].[Сумма], [Период].[Период].Lag(15)),
IIF((not IsEmpty(([Measures].[Сумма], [Период].[Период].lag(16))) and ([Measures].[Сумма], [Период].[Период].lag(16)) <>0) , ([Measures].[Сумма], [Период].[Период].CurrentMember)/([Measures].[Сумма], [Период].[Период].Lag(16)),
IIF((not IsEmpty(([Measures].[Сумма], [Период].[Период].lag(17))) and ([Measures].[Сумма], [Период].[Период].lag(17)) <>0) , ([Measures].[Сумма], [Период].[Период].CurrentMember)/([Measures].[Сумма], [Период].[Период].Lag(17)),
IIF((not IsEmpty(([Measures].[Сумма], [Период].[Период].lag(18))) and ([Measures].[Сумма], [Период].[Период].lag(18)) <>0) , ([Measures].[Сумма], [Период].[Период].CurrentMember)/([Measures].[Сумма], [Период].[Период].Lag(18)),
IIF((not IsEmpty(([Measures].[Сумма], [Период].[Период].lag(19))) and ([Measures].[Сумма], [Период].[Период].lag(19)) <>0) , ([Measures].[Сумма], [Период].[Период].CurrentMember)/([Measures].[Сумма], [Период].[Период].Lag(19)),
IIF((not IsEmpty(([Measures].[Сумма], [Период].[Период].lag(20))) and ([Measures].[Сумма], [Период].[Период].lag(20)) <>0) , ([Measures].[Сумма], [Период].[Период].CurrentMember)/([Measures].[Сумма], [Период].[Период].Lag(20)),
IIF((not IsEmpty(([Measures].[Сумма], [Период].[Период].lag(21))) and ([Measures].[Сумма], [Период].[Период].lag(21)) <>0) , ([Measures].[Сумма], [Период].[Период].CurrentMember)/([Measures].[Сумма], [Период].[Период].Lag(21)),
IIF((not IsEmpty(([Measures].[Сумма], [Период].[Период].lag(22))) and ([Measures].[Сумма], [Период].[Период].lag(22)) <>0) , ([Measures].[Сумма], [Период].[Период].CurrentMember)/([Measures].[Сумма], [Период].[Период].Lag(22)),
IIF((not IsEmpty(([Measures].[Сумма], [Период].[Период].lag(23))) and ([Measures].[Сумма], [Период].[Период].lag(23)) <>0) , ([Measures].[Сумма], [Период].[Период].CurrentMember)/([Measures].[Сумма], [Период].[Период].Lag(23)),
IIF((not IsEmpty(([Measures].[Сумма], [Период].[Период].lag(24))) and ([Measures].[Сумма], [Период].[Период].lag(24)) <>0) , ([Measures].[Сумма], [Период].[Период].CurrentMember)/([Measures].[Сумма], [Период].[Период].Lag(24)),
IIF((not IsEmpty(([Measures].[Сумма], [Период].[Период].lag(25))) and ([Measures].[Сумма], [Период].[Период].lag(25)) <>0) , ([Measures].[Сумма], [Период].[Период].CurrentMember)/([Measures].[Сумма], [Период].[Период].Lag(25)),
IIF((not IsEmpty(([Measures].[Сумма], [Период].[Период].lag(26))) and ([Measures].[Сумма], [Период].[Период].lag(26)) <>0) , ([Measures].[Сумма], [Период].[Период].CurrentMember)/([Measures].[Сумма], [Период].[Период].Lag(26)),
IIF((not IsEmpty(([Measures].[Сумма], [Период].[Период].lag(27))) and ([Measures].[Сумма], [Период].[Период].lag(27)) <>0) , ([Measures].[Сумма], [Период].[Период].CurrentMember)/([Measures].[Сумма], [Период].[Период].Lag(27)),
IIF((not IsEmpty(([Measures].[Сумма], [Период].[Период].lag(28))) and ([Measures].[Сумма], [Период].[Период].lag(28)) <>0) , ([Measures].[Сумма], [Период].[Период].CurrentMember)/([Measures].[Сумма], [Период].[Период].Lag(28)),
IIF((not IsEmpty(([Measures].[Сумма], [Период].[Период].lag(29))) and ([Measures].[Сумма], [Период].[Период].lag(29)) <>0) , ([Measures].[Сумма], [Период].[Период].CurrentMember)/([Measures].[Сумма], [Период].[Период].Lag(29)),
IIF((not IsEmpty(([Measures].[Сумма], [Период].[Период].lag(30))) and ([Measures].[Сумма], [Период].[Период].lag(30)) <>0) , ([Measures].[Сумма], [Период].[Период].CurrentMember)/([Measures].[Сумма], [Период].[Период].Lag(30)),
IIF((not IsEmpty(([Measures].[Сумма], [Период].[Период].lag(31))) and ([Measures].[Сумма], [Период].[Период].lag(31)) <>0) , ([Measures].[Сумма], [Период].[Период].CurrentMember)/([Measures].[Сумма], [Период].[Период].Lag(31)),
null
))))))))))))))))))))))))))))))))', FORMAT_STRING = 'Percent']]></property>
    </CubeCommand>
  </CubeCommands>
  <Partitions>
    <Partition method="Add" name="Год_1998_2000" ClassType="19" SubClassType="0" Description="" OlapMode="0" AggregationPrefix="УФК_СводФУ_Год_1998_2000_" EstimatedRows="28118" IsReadWrite="false">
      <property name="SourceTable"><![CDATA["DV"."F_F_BUDGETINCOMINGSTULA"]]></property>
      <property name="SourceTableAlias"><![CDATA["DV"."F_F_BUDGETINCOMINGSTULA"]]></property>
      <property name="SourceTableFilter"><![CDATA["DV"."F_F_BUDGETINCOMINGSTULA"."REFYEARDAYUNV" between 19980000 and 20009999]]></property>
      <property name="FromClause"><![CDATA["DV"."F_F_BUDGETINCOMINGSTULA", "DV"."DV_KD_UFK2", "DV"."DV_OKATO_UFK2", "DV"."BV_OKATO_BRIDGE", "DV"."DV_REGIONS_UFK2", "DV"."BV_REGIONS_BRIDGE", "DV"."FX_FX_BUDGETLEVELS", "DV"."DATASOURCES", "DV"."BV_KD_BRIDGE", "DV"."BV_KD_BRIDGEPLAN", "DV"."BV_REGIONS_BRIDGEPLAN", "DV"."BV_KIF_BRIDGEPLAN", "DV"."BV_KIF_BRIDGE", "DV"."BV_KVSR_BRIDGE", "DV"."BV_PROGRAMS_BRIDGE", "DV"."D_DOC_LIST", "DV"."DV_FX_DATE_YEARDAYUNV", "DV"."FX_DATE_YEARDAYUNV"]]></property>
      <property name="JoinClause"><![CDATA[("DV"."F_F_BUDGETINCOMINGSTULA"."REFKD"="DV"."DV_KD_UFK2"."ID") AND ("DV"."F_F_BUDGETINCOMINGSTULA"."REFOKATO"="DV"."DV_OKATO_UFK2"."ID") AND ("DV"."DV_OKATO_UFK2"."REFBRIDGEOKATO"="DV"."BV_OKATO_BRIDGE"."ID") AND ("DV"."F_F_BUDGETINCOMINGSTULA"."REFREGIONS"="DV"."DV_REGIONS_UFK2"."ID") AND ("DV"."DV_REGIONS_UFK2"."REFBRIDGEREGIONS"="DV"."BV_REGIONS_BRIDGE"."ID") AND ("DV"."F_F_BUDGETINCOMINGSTULA"."REFBUDGETLEVELS"="DV"."FX_FX_BUDGETLEVELS"."ID") AND ("DV"."F_F_BUDGETINCOMINGSTULA"."SOURCEID"="DV"."DATASOURCES"."ID") AND ("DV"."DV_KD_UFK2"."REFBRIDGEKD"="DV"."BV_KD_BRIDGE"."ID") AND ("DV"."DV_KD_UFK2"."REFBRIDGEKDPLAN"="DV"."BV_KD_BRIDGEPLAN"."ID") AND ("DV"."DV_REGIONS_UFK2"."REFBRIDGEREGIONSPLAN"="DV"."BV_REGIONS_BRIDGEPLAN"."ID") AND ("DV"."DV_KD_UFK2"."REFKIFBRIDGEPLAN"="DV"."BV_KIF_BRIDGEPLAN"."ID") AND ("DV"."DV_KD_UFK2"."REFKIFBRIDGE"="DV"."BV_KIF_BRIDGE"."ID") AND ("DV"."DV_KD_UFK2"."REFKVSRBRIDGE"="DV"."BV_KVSR_BRIDGE"."ID") AND ("DV"."DV_KD_UFK2"."REFPROGRAMSBRIDGE"="DV"."BV_PROGRAMS_BRIDGE"."ID") AND ("DV"."F_F_BUDGETINCOMINGSTULA"."REFDOC"="DV"."D_DOC_LIST"."ID") AND ("DV"."F_F_BUDGETINCOMINGSTULA"."REFFKDAY"="DV"."DV_FX_DATE_YEARDAYUNV"."ID") AND ("DV"."F_F_BUDGETINCOMINGSTULA"."REFYEARDAYUNV"="DV"."FX_DATE_YEARDAYUNV"."ID")]]></property>
      <property name="DrillThroughColumns"><![CDATA[]]></property>
      <property name="DrillThroughFilter"><![CDATA[]]></property>
      <property name="DrillThroughFrom"><![CDATA[]]></property>
      <property name="DrillThroughJoins"><![CDATA[]]></property>
      <CustomProperties>
        <Property name="ID" datatype="8"><![CDATA[0A274A90-DC38-4CAF-9165-13757D69F628]]></Property>
        <Property name="ObjectKey" datatype="8"><![CDATA[826d5da9-c9cc-4f8d-9432-d7357fda4677]]></Property>
      </CustomProperties>
      <DataSources>
        <DataSource method="Add" name="dv" ClassType="6" SubClassType="0">
          <CustomProperties>
            <Property name="ID" datatype="8"><![CDATA[af4c64e8-2b41-4fab-a1fa-acd52b27625e]]></Property>
          </CustomProperties>
        </DataSource>
      </DataSources>
      <Aggregations />
    </Partition>
    <Partition method="Add" name="Год_2001" ClassType="19" SubClassType="0" Description="" OlapMode="0" AggregationPrefix="ПоступлениявбюджетыТула_Год2001_" EstimatedRows="837775" IsReadWrite="false">
      <property name="SourceTable"><![CDATA["DV"."F_F_BUDGETINCOMINGSTULA"]]></property>
      <property name="SourceTableAlias"><![CDATA["DV"."F_F_BUDGETINCOMINGSTULA"]]></property>
      <property name="SourceTableFilter"><![CDATA["DV"."F_F_BUDGETINCOMINGSTULA"."REFYEARDAYUNV" between 20010000 and 20019999]]></property>
      <property name="FromClause"><![CDATA["DV"."F_F_BUDGETINCOMINGSTULA", "DV"."DV_KD_UFK2", "DV"."DV_OKATO_UFK2", "DV"."BV_OKATO_BRIDGE", "DV"."DV_REGIONS_UFK2", "DV"."BV_REGIONS_BRIDGE", "DV"."FX_FX_BUDGETLEVELS", "DV"."DATASOURCES", "DV"."BV_KD_BRIDGE", "DV"."BV_KD_BRIDGEPLAN", "DV"."BV_REGIONS_BRIDGEPLAN", "DV"."BV_KIF_BRIDGEPLAN", "DV"."BV_KIF_BRIDGE", "DV"."BV_KVSR_BRIDGE", "DV"."BV_PROGRAMS_BRIDGE", "DV"."D_DOC_LIST", "DV"."DV_FX_DATE_YEARDAYUNV", "DV"."FX_DATE_YEARDAYUNV"]]></property>
      <property name="JoinClause"><![CDATA[("DV"."F_F_BUDGETINCOMINGSTULA"."REFKD"="DV"."DV_KD_UFK2"."ID") AND ("DV"."F_F_BUDGETINCOMINGSTULA"."REFOKATO"="DV"."DV_OKATO_UFK2"."ID") AND ("DV"."DV_OKATO_UFK2"."REFBRIDGEOKATO"="DV"."BV_OKATO_BRIDGE"."ID") AND ("DV"."F_F_BUDGETINCOMINGSTULA"."REFREGIONS"="DV"."DV_REGIONS_UFK2"."ID") AND ("DV"."DV_REGIONS_UFK2"."REFBRIDGEREGIONS"="DV"."BV_REGIONS_BRIDGE"."ID") AND ("DV"."F_F_BUDGETINCOMINGSTULA"."REFBUDGETLEVELS"="DV"."FX_FX_BUDGETLEVELS"."ID") AND ("DV"."F_F_BUDGETINCOMINGSTULA"."SOURCEID"="DV"."DATASOURCES"."ID") AND ("DV"."DV_KD_UFK2"."REFBRIDGEKD"="DV"."BV_KD_BRIDGE"."ID") AND ("DV"."DV_KD_UFK2"."REFBRIDGEKDPLAN"="DV"."BV_KD_BRIDGEPLAN"."ID") AND ("DV"."DV_REGIONS_UFK2"."REFBRIDGEREGIONSPLAN"="DV"."BV_REGIONS_BRIDGEPLAN"."ID") AND ("DV"."DV_KD_UFK2"."REFKIFBRIDGEPLAN"="DV"."BV_KIF_BRIDGEPLAN"."ID") AND ("DV"."DV_KD_UFK2"."REFKIFBRIDGE"="DV"."BV_KIF_BRIDGE"."ID") AND ("DV"."DV_KD_UFK2"."REFKVSRBRIDGE"="DV"."BV_KVSR_BRIDGE"."ID") AND ("DV"."DV_KD_UFK2"."REFPROGRAMSBRIDGE"="DV"."BV_PROGRAMS_BRIDGE"."ID") AND ("DV"."F_F_BUDGETINCOMINGSTULA"."REFDOC"="DV"."D_DOC_LIST"."ID") AND ("DV"."F_F_BUDGETINCOMINGSTULA"."REFFKDAY"="DV"."DV_FX_DATE_YEARDAYUNV"."ID") AND ("DV"."F_F_BUDGETINCOMINGSTULA"."REFYEARDAYUNV"="DV"."FX_DATE_YEARDAYUNV"."ID")]]></property>
      <property name="DrillThroughColumns"><![CDATA[]]></property>
      <property name="DrillThroughFilter"><![CDATA[]]></property>
      <property name="DrillThroughFrom"><![CDATA[]]></property>
      <property name="DrillThroughJoins"><![CDATA[]]></property>
      <CustomProperties>
        <Property name="ID" datatype="8"><![CDATA[8399b443-2bbc-42b0-8a04-7edd4239b54e]]></Property>
        <Property name="ObjectKey" datatype="8"><![CDATA[826d5da9-c9cc-4f8d-9432-d7357fda4677]]></Property>
      </CustomProperties>
      <DataSources>
        <DataSource method="Add" name="dv" ClassType="6" SubClassType="0">
          <CustomProperties>
            <Property name="ID" datatype="8"><![CDATA[af4c64e8-2b41-4fab-a1fa-acd52b27625e]]></Property>
          </CustomProperties>
        </DataSource>
      </DataSources>
      <Aggregations />
    </Partition>
    <Partition method="Add" name="Год_2002" ClassType="19" SubClassType="0" Description="" OlapMode="0" AggregationPrefix="ПоступлениявбюджетыТула_Год2002_" EstimatedRows="837775" IsReadWrite="false">
      <property name="SourceTable"><![CDATA["DV"."F_F_BUDGETINCOMINGSTULA"]]></property>
      <property name="SourceTableAlias"><![CDATA["DV"."F_F_BUDGETINCOMINGSTULA"]]></property>
      <property name="SourceTableFilter"><![CDATA["DV"."F_F_BUDGETINCOMINGSTULA"."REFYEARDAYUNV" between 20020000 and 20029999]]></property>
      <property name="FromClause"><![CDATA["DV"."F_F_BUDGETINCOMINGSTULA", "DV"."DV_KD_UFK2", "DV"."DV_OKATO_UFK2", "DV"."BV_OKATO_BRIDGE", "DV"."DV_REGIONS_UFK2", "DV"."BV_REGIONS_BRIDGE", "DV"."FX_FX_BUDGETLEVELS", "DV"."DATASOURCES", "DV"."BV_KD_BRIDGE", "DV"."BV_KD_BRIDGEPLAN", "DV"."BV_REGIONS_BRIDGEPLAN", "DV"."BV_KIF_BRIDGEPLAN", "DV"."BV_KIF_BRIDGE", "DV"."BV_KVSR_BRIDGE", "DV"."BV_PROGRAMS_BRIDGE", "DV"."D_DOC_LIST", "DV"."DV_FX_DATE_YEARDAYUNV", "DV"."FX_DATE_YEARDAYUNV"]]></property>
      <property name="JoinClause"><![CDATA[("DV"."F_F_BUDGETINCOMINGSTULA"."REFKD"="DV"."DV_KD_UFK2"."ID") AND ("DV"."F_F_BUDGETINCOMINGSTULA"."REFOKATO"="DV"."DV_OKATO_UFK2"."ID") AND ("DV"."DV_OKATO_UFK2"."REFBRIDGEOKATO"="DV"."BV_OKATO_BRIDGE"."ID") AND ("DV"."F_F_BUDGETINCOMINGSTULA"."REFREGIONS"="DV"."DV_REGIONS_UFK2"."ID") AND ("DV"."DV_REGIONS_UFK2"."REFBRIDGEREGIONS"="DV"."BV_REGIONS_BRIDGE"."ID") AND ("DV"."F_F_BUDGETINCOMINGSTULA"."REFBUDGETLEVELS"="DV"."FX_FX_BUDGETLEVELS"."ID") AND ("DV"."F_F_BUDGETINCOMINGSTULA"."SOURCEID"="DV"."DATASOURCES"."ID") AND ("DV"."DV_KD_UFK2"."REFBRIDGEKD"="DV"."BV_KD_BRIDGE"."ID") AND ("DV"."DV_KD_UFK2"."REFBRIDGEKDPLAN"="DV"."BV_KD_BRIDGEPLAN"."ID") AND ("DV"."DV_REGIONS_UFK2"."REFBRIDGEREGIONSPLAN"="DV"."BV_REGIONS_BRIDGEPLAN"."ID") AND ("DV"."DV_KD_UFK2"."REFKIFBRIDGEPLAN"="DV"."BV_KIF_BRIDGEPLAN"."ID") AND ("DV"."DV_KD_UFK2"."REFKIFBRIDGE"="DV"."BV_KIF_BRIDGE"."ID") AND ("DV"."DV_KD_UFK2"."REFKVSRBRIDGE"="DV"."BV_KVSR_BRIDGE"."ID") AND ("DV"."DV_KD_UFK2"."REFPROGRAMSBRIDGE"="DV"."BV_PROGRAMS_BRIDGE"."ID") AND ("DV"."F_F_BUDGETINCOMINGSTULA"."REFDOC"="DV"."D_DOC_LIST"."ID") AND ("DV"."F_F_BUDGETINCOMINGSTULA"."REFFKDAY"="DV"."DV_FX_DATE_YEARDAYUNV"."ID") AND ("DV"."F_F_BUDGETINCOMINGSTULA"."REFYEARDAYUNV"="DV"."FX_DATE_YEARDAYUNV"."ID")]]></property>
      <property name="DrillThroughColumns"><![CDATA[]]></property>
      <property name="DrillThroughFilter"><![CDATA[]]></property>
      <property name="DrillThroughFrom"><![CDATA[]]></property>
      <property name="DrillThroughJoins"><![CDATA[]]></property>
      <CustomProperties>
        <Property name="ID" datatype="8"><![CDATA[f2e16803-682d-4e11-bb4b-c67f5dcc64a2]]></Property>
        <Property name="ObjectKey" datatype="8"><![CDATA[826d5da9-c9cc-4f8d-9432-d7357fda4677]]></Property>
      </CustomProperties>
      <DataSources>
        <DataSource method="Add" name="dv" ClassType="6" SubClassType="0">
          <CustomProperties>
            <Property name="ID" datatype="8"><![CDATA[af4c64e8-2b41-4fab-a1fa-acd52b27625e]]></Property>
          </CustomProperties>
        </DataSource>
      </DataSources>
      <Aggregations />
    </Partition>
    <Partition method="Add" name="Год_2003" ClassType="19" SubClassType="0" Description="" OlapMode="0" AggregationPrefix="ПоступлениявбюджетыТула_Год2003_" EstimatedRows="837775" IsReadWrite="false">
      <property name="SourceTable"><![CDATA["DV"."F_F_BUDGETINCOMINGSTULA"]]></property>
      <property name="SourceTableAlias"><![CDATA["DV"."F_F_BUDGETINCOMINGSTULA"]]></property>
      <property name="SourceTableFilter"><![CDATA["DV"."F_F_BUDGETINCOMINGSTULA"."REFYEARDAYUNV" between 20030000 and 20039999]]></property>
      <property name="FromClause"><![CDATA["DV"."F_F_BUDGETINCOMINGSTULA", "DV"."DV_KD_UFK2", "DV"."DV_OKATO_UFK2", "DV"."BV_OKATO_BRIDGE", "DV"."DV_REGIONS_UFK2", "DV"."BV_REGIONS_BRIDGE", "DV"."FX_FX_BUDGETLEVELS", "DV"."DATASOURCES", "DV"."BV_KD_BRIDGE", "DV"."BV_KD_BRIDGEPLAN", "DV"."BV_REGIONS_BRIDGEPLAN", "DV"."BV_KIF_BRIDGEPLAN", "DV"."BV_KIF_BRIDGE", "DV"."BV_KVSR_BRIDGE", "DV"."BV_PROGRAMS_BRIDGE", "DV"."D_DOC_LIST", "DV"."DV_FX_DATE_YEARDAYUNV", "DV"."FX_DATE_YEARDAYUNV"]]></property>
      <property name="JoinClause"><![CDATA[("DV"."F_F_BUDGETINCOMINGSTULA"."REFKD"="DV"."DV_KD_UFK2"."ID") AND ("DV"."F_F_BUDGETINCOMINGSTULA"."REFOKATO"="DV"."DV_OKATO_UFK2"."ID") AND ("DV"."DV_OKATO_UFK2"."REFBRIDGEOKATO"="DV"."BV_OKATO_BRIDGE"."ID") AND ("DV"."F_F_BUDGETINCOMINGSTULA"."REFREGIONS"="DV"."DV_REGIONS_UFK2"."ID") AND ("DV"."DV_REGIONS_UFK2"."REFBRIDGEREGIONS"="DV"."BV_REGIONS_BRIDGE"."ID") AND ("DV"."F_F_BUDGETINCOMINGSTULA"."REFBUDGETLEVELS"="DV"."FX_FX_BUDGETLEVELS"."ID") AND ("DV"."F_F_BUDGETINCOMINGSTULA"."SOURCEID"="DV"."DATASOURCES"."ID") AND ("DV"."DV_KD_UFK2"."REFBRIDGEKD"="DV"."BV_KD_BRIDGE"."ID") AND ("DV"."DV_KD_UFK2"."REFBRIDGEKDPLAN"="DV"."BV_KD_BRIDGEPLAN"."ID") AND ("DV"."DV_REGIONS_UFK2"."REFBRIDGEREGIONSPLAN"="DV"."BV_REGIONS_BRIDGEPLAN"."ID") AND ("DV"."DV_KD_UFK2"."REFKIFBRIDGEPLAN"="DV"."BV_KIF_BRIDGEPLAN"."ID") AND ("DV"."DV_KD_UFK2"."REFKIFBRIDGE"="DV"."BV_KIF_BRIDGE"."ID") AND ("DV"."DV_KD_UFK2"."REFKVSRBRIDGE"="DV"."BV_KVSR_BRIDGE"."ID") AND ("DV"."DV_KD_UFK2"."REFPROGRAMSBRIDGE"="DV"."BV_PROGRAMS_BRIDGE"."ID") AND ("DV"."F_F_BUDGETINCOMINGSTULA"."REFDOC"="DV"."D_DOC_LIST"."ID") AND ("DV"."F_F_BUDGETINCOMINGSTULA"."REFFKDAY"="DV"."DV_FX_DATE_YEARDAYUNV"."ID") AND ("DV"."F_F_BUDGETINCOMINGSTULA"."REFYEARDAYUNV"="DV"."FX_DATE_YEARDAYUNV"."ID")]]></property>
      <property name="DrillThroughColumns"><![CDATA[]]></property>
      <property name="DrillThroughFilter"><![CDATA[]]></property>
      <property name="DrillThroughFrom"><![CDATA[]]></property>
      <property name="DrillThroughJoins"><![CDATA[]]></property>
      <CustomProperties>
        <Property name="ID" datatype="8"><![CDATA[f76137a9-70a8-40d0-ba37-ca3eae1768f6]]></Property>
        <Property name="ObjectKey" datatype="8"><![CDATA[826d5da9-c9cc-4f8d-9432-d7357fda4677]]></Property>
      </CustomProperties>
      <DataSources>
        <DataSource method="Add" name="dv" ClassType="6" SubClassType="0">
          <CustomProperties>
            <Property name="ID" datatype="8"><![CDATA[af4c64e8-2b41-4fab-a1fa-acd52b27625e]]></Property>
          </CustomProperties>
        </DataSource>
      </DataSources>
      <Aggregations />
    </Partition>
    <Partition method="Add" name="Год_2004" ClassType="19" SubClassType="0" Description="" OlapMode="0" AggregationPrefix="ПоступлениявбюджетыТула_Год2004_" EstimatedRows="837775" IsReadWrite="false">
      <property name="SourceTable"><![CDATA["DV"."F_F_BUDGETINCOMINGSTULA"]]></property>
      <property name="SourceTableAlias"><![CDATA["DV"."F_F_BUDGETINCOMINGSTULA"]]></property>
      <property name="SourceTableFilter"><![CDATA["DV"."F_F_BUDGETINCOMINGSTULA"."REFYEARDAYUNV" between 20040000 and 20049999]]></property>
      <property name="FromClause"><![CDATA["DV"."F_F_BUDGETINCOMINGSTULA", "DV"."DV_KD_UFK2", "DV"."DV_OKATO_UFK2", "DV"."BV_OKATO_BRIDGE", "DV"."DV_REGIONS_UFK2", "DV"."BV_REGIONS_BRIDGE", "DV"."FX_FX_BUDGETLEVELS", "DV"."DATASOURCES", "DV"."BV_KD_BRIDGE", "DV"."BV_KD_BRIDGEPLAN", "DV"."BV_REGIONS_BRIDGEPLAN", "DV"."BV_KIF_BRIDGEPLAN", "DV"."BV_KIF_BRIDGE", "DV"."BV_KVSR_BRIDGE", "DV"."BV_PROGRAMS_BRIDGE", "DV"."D_DOC_LIST", "DV"."DV_FX_DATE_YEARDAYUNV", "DV"."FX_DATE_YEARDAYUNV"]]></property>
      <property name="JoinClause"><![CDATA[("DV"."F_F_BUDGETINCOMINGSTULA"."REFKD"="DV"."DV_KD_UFK2"."ID") AND ("DV"."F_F_BUDGETINCOMINGSTULA"."REFOKATO"="DV"."DV_OKATO_UFK2"."ID") AND ("DV"."DV_OKATO_UFK2"."REFBRIDGEOKATO"="DV"."BV_OKATO_BRIDGE"."ID") AND ("DV"."F_F_BUDGETINCOMINGSTULA"."REFREGIONS"="DV"."DV_REGIONS_UFK2"."ID") AND ("DV"."DV_REGIONS_UFK2"."REFBRIDGEREGIONS"="DV"."BV_REGIONS_BRIDGE"."ID") AND ("DV"."F_F_BUDGETINCOMINGSTULA"."REFBUDGETLEVELS"="DV"."FX_FX_BUDGETLEVELS"."ID") AND ("DV"."F_F_BUDGETINCOMINGSTULA"."SOURCEID"="DV"."DATASOURCES"."ID") AND ("DV"."DV_KD_UFK2"."REFBRIDGEKD"="DV"."BV_KD_BRIDGE"."ID") AND ("DV"."DV_KD_UFK2"."REFBRIDGEKDPLAN"="DV"."BV_KD_BRIDGEPLAN"."ID") AND ("DV"."DV_REGIONS_UFK2"."REFBRIDGEREGIONSPLAN"="DV"."BV_REGIONS_BRIDGEPLAN"."ID") AND ("DV"."DV_KD_UFK2"."REFKIFBRIDGEPLAN"="DV"."BV_KIF_BRIDGEPLAN"."ID") AND ("DV"."DV_KD_UFK2"."REFKIFBRIDGE"="DV"."BV_KIF_BRIDGE"."ID") AND ("DV"."DV_KD_UFK2"."REFKVSRBRIDGE"="DV"."BV_KVSR_BRIDGE"."ID") AND ("DV"."DV_KD_UFK2"."REFPROGRAMSBRIDGE"="DV"."BV_PROGRAMS_BRIDGE"."ID") AND ("DV"."F_F_BUDGETINCOMINGSTULA"."REFDOC"="DV"."D_DOC_LIST"."ID") AND ("DV"."F_F_BUDGETINCOMINGSTULA"."REFFKDAY"="DV"."DV_FX_DATE_YEARDAYUNV"."ID") AND ("DV"."F_F_BUDGETINCOMINGSTULA"."REFYEARDAYUNV"="DV"."FX_DATE_YEARDAYUNV"."ID")]]></property>
      <property name="DrillThroughColumns"><![CDATA[]]></property>
      <property name="DrillThroughFilter"><![CDATA[]]></property>
      <property name="DrillThroughFrom"><![CDATA[]]></property>
      <property name="DrillThroughJoins"><![CDATA[]]></property>
      <CustomProperties>
        <Property name="ID" datatype="8"><![CDATA[ac33467c-bead-4422-892a-0532ca5fda03]]></Property>
        <Property name="ObjectKey" datatype="8"><![CDATA[826d5da9-c9cc-4f8d-9432-d7357fda4677]]></Property>
      </CustomProperties>
      <DataSources>
        <DataSource method="Add" name="dv" ClassType="6" SubClassType="0">
          <CustomProperties>
            <Property name="ID" datatype="8"><![CDATA[af4c64e8-2b41-4fab-a1fa-acd52b27625e]]></Property>
          </CustomProperties>
        </DataSource>
      </DataSources>
      <Aggregations />
    </Partition>
    <Partition method="Add" name="Год_2005" ClassType="19" SubClassType="0" Description="" OlapMode="0" AggregationPrefix="ПоступлениявбюджетыТула_Год2005_" EstimatedRows="837775" IsReadWrite="false">
      <property name="SourceTable"><![CDATA["DV"."F_F_BUDGETINCOMINGSTULA"]]></property>
      <property name="SourceTableAlias"><![CDATA["DV"."F_F_BUDGETINCOMINGSTULA"]]></property>
      <property name="SourceTableFilter"><![CDATA["DV"."F_F_BUDGETINCOMINGSTULA"."REFYEARDAYUNV" between 20050000 and 20059999]]></property>
      <property name="FromClause"><![CDATA["DV"."F_F_BUDGETINCOMINGSTULA", "DV"."DV_KD_UFK2", "DV"."DV_OKATO_UFK2", "DV"."BV_OKATO_BRIDGE", "DV"."DV_REGIONS_UFK2", "DV"."BV_REGIONS_BRIDGE", "DV"."FX_FX_BUDGETLEVELS", "DV"."DATASOURCES", "DV"."BV_KD_BRIDGE", "DV"."BV_KD_BRIDGEPLAN", "DV"."BV_REGIONS_BRIDGEPLAN", "DV"."BV_KIF_BRIDGEPLAN", "DV"."BV_KIF_BRIDGE", "DV"."BV_KVSR_BRIDGE", "DV"."BV_PROGRAMS_BRIDGE", "DV"."D_DOC_LIST", "DV"."DV_FX_DATE_YEARDAYUNV", "DV"."FX_DATE_YEARDAYUNV"]]></property>
      <property name="JoinClause"><![CDATA[("DV"."F_F_BUDGETINCOMINGSTULA"."REFKD"="DV"."DV_KD_UFK2"."ID") AND ("DV"."F_F_BUDGETINCOMINGSTULA"."REFOKATO"="DV"."DV_OKATO_UFK2"."ID") AND ("DV"."DV_OKATO_UFK2"."REFBRIDGEOKATO"="DV"."BV_OKATO_BRIDGE"."ID") AND ("DV"."F_F_BUDGETINCOMINGSTULA"."REFREGIONS"="DV"."DV_REGIONS_UFK2"."ID") AND ("DV"."DV_REGIONS_UFK2"."REFBRIDGEREGIONS"="DV"."BV_REGIONS_BRIDGE"."ID") AND ("DV"."F_F_BUDGETINCOMINGSTULA"."REFBUDGETLEVELS"="DV"."FX_FX_BUDGETLEVELS"."ID") AND ("DV"."F_F_BUDGETINCOMINGSTULA"."SOURCEID"="DV"."DATASOURCES"."ID") AND ("DV"."DV_KD_UFK2"."REFBRIDGEKD"="DV"."BV_KD_BRIDGE"."ID") AND ("DV"."DV_KD_UFK2"."REFBRIDGEKDPLAN"="DV"."BV_KD_BRIDGEPLAN"."ID") AND ("DV"."DV_REGIONS_UFK2"."REFBRIDGEREGIONSPLAN"="DV"."BV_REGIONS_BRIDGEPLAN"."ID") AND ("DV"."DV_KD_UFK2"."REFKIFBRIDGEPLAN"="DV"."BV_KIF_BRIDGEPLAN"."ID") AND ("DV"."DV_KD_UFK2"."REFKIFBRIDGE"="DV"."BV_KIF_BRIDGE"."ID") AND ("DV"."DV_KD_UFK2"."REFKVSRBRIDGE"="DV"."BV_KVSR_BRIDGE"."ID") AND ("DV"."DV_KD_UFK2"."REFPROGRAMSBRIDGE"="DV"."BV_PROGRAMS_BRIDGE"."ID") AND ("DV"."F_F_BUDGETINCOMINGSTULA"."REFDOC"="DV"."D_DOC_LIST"."ID") AND ("DV"."F_F_BUDGETINCOMINGSTULA"."REFFKDAY"="DV"."DV_FX_DATE_YEARDAYUNV"."ID") AND ("DV"."F_F_BUDGETINCOMINGSTULA"."REFYEARDAYUNV"="DV"."FX_DATE_YEARDAYUNV"."ID")]]></property>
      <property name="DrillThroughColumns"><![CDATA[]]></property>
      <property name="DrillThroughFilter"><![CDATA[]]></property>
      <property name="DrillThroughFrom"><![CDATA[]]></property>
      <property name="DrillThroughJoins"><![CDATA[]]></property>
      <CustomProperties>
        <Property name="ID" datatype="8"><![CDATA[27211d1f-bbfe-4070-9c89-835c603d2ab5]]></Property>
        <Property name="ObjectKey" datatype="8"><![CDATA[826d5da9-c9cc-4f8d-9432-d7357fda4677]]></Property>
      </CustomProperties>
      <DataSources>
        <DataSource method="Add" name="dv" ClassType="6" SubClassType="0">
          <CustomProperties>
            <Property name="ID" datatype="8"><![CDATA[af4c64e8-2b41-4fab-a1fa-acd52b27625e]]></Property>
          </CustomProperties>
        </DataSource>
      </DataSources>
      <Aggregations />
    </Partition>
    <Partition method="Add" name="Год_2006" ClassType="19" SubClassType="0" Description="" OlapMode="0" AggregationPrefix="ПоступлениявбюджетыТула_Год2006_" EstimatedRows="837775" IsReadWrite="false">
      <property name="SourceTable"><![CDATA["DV"."F_F_BUDGETINCOMINGSTULA"]]></property>
      <property name="SourceTableAlias"><![CDATA["DV"."F_F_BUDGETINCOMINGSTULA"]]></property>
      <property name="SourceTableFilter"><![CDATA["DV"."F_F_BUDGETINCOMINGSTULA"."REFYEARDAYUNV" between 20060000 and 20069999]]></property>
      <property name="FromClause"><![CDATA["DV"."F_F_BUDGETINCOMINGSTULA", "DV"."DV_KD_UFK2", "DV"."DV_OKATO_UFK2", "DV"."BV_OKATO_BRIDGE", "DV"."DV_REGIONS_UFK2", "DV"."BV_REGIONS_BRIDGE", "DV"."FX_FX_BUDGETLEVELS", "DV"."DATASOURCES", "DV"."BV_KD_BRIDGE", "DV"."BV_KD_BRIDGEPLAN", "DV"."BV_REGIONS_BRIDGEPLAN", "DV"."BV_KIF_BRIDGEPLAN", "DV"."BV_KIF_BRIDGE", "DV"."BV_KVSR_BRIDGE", "DV"."BV_PROGRAMS_BRIDGE", "DV"."D_DOC_LIST", "DV"."DV_FX_DATE_YEARDAYUNV", "DV"."FX_DATE_YEARDAYUNV"]]></property>
      <property name="JoinClause"><![CDATA[("DV"."F_F_BUDGETINCOMINGSTULA"."REFKD"="DV"."DV_KD_UFK2"."ID") AND ("DV"."F_F_BUDGETINCOMINGSTULA"."REFOKATO"="DV"."DV_OKATO_UFK2"."ID") AND ("DV"."DV_OKATO_UFK2"."REFBRIDGEOKATO"="DV"."BV_OKATO_BRIDGE"."ID") AND ("DV"."F_F_BUDGETINCOMINGSTULA"."REFREGIONS"="DV"."DV_REGIONS_UFK2"."ID") AND ("DV"."DV_REGIONS_UFK2"."REFBRIDGEREGIONS"="DV"."BV_REGIONS_BRIDGE"."ID") AND ("DV"."F_F_BUDGETINCOMINGSTULA"."REFBUDGETLEVELS"="DV"."FX_FX_BUDGETLEVELS"."ID") AND ("DV"."F_F_BUDGETINCOMINGSTULA"."SOURCEID"="DV"."DATASOURCES"."ID") AND ("DV"."DV_KD_UFK2"."REFBRIDGEKD"="DV"."BV_KD_BRIDGE"."ID") AND ("DV"."DV_KD_UFK2"."REFBRIDGEKDPLAN"="DV"."BV_KD_BRIDGEPLAN"."ID") AND ("DV"."DV_REGIONS_UFK2"."REFBRIDGEREGIONSPLAN"="DV"."BV_REGIONS_BRIDGEPLAN"."ID") AND ("DV"."DV_KD_UFK2"."REFKIFBRIDGEPLAN"="DV"."BV_KIF_BRIDGEPLAN"."ID") AND ("DV"."DV_KD_UFK2"."REFKIFBRIDGE"="DV"."BV_KIF_BRIDGE"."ID") AND ("DV"."DV_KD_UFK2"."REFKVSRBRIDGE"="DV"."BV_KVSR_BRIDGE"."ID") AND ("DV"."DV_KD_UFK2"."REFPROGRAMSBRIDGE"="DV"."BV_PROGRAMS_BRIDGE"."ID") AND ("DV"."F_F_BUDGETINCOMINGSTULA"."REFDOC"="DV"."D_DOC_LIST"."ID") AND ("DV"."F_F_BUDGETINCOMINGSTULA"."REFFKDAY"="DV"."DV_FX_DATE_YEARDAYUNV"."ID") AND ("DV"."F_F_BUDGETINCOMINGSTULA"."REFYEARDAYUNV"="DV"."FX_DATE_YEARDAYUNV"."ID")]]></property>
      <property name="DrillThroughColumns"><![CDATA[]]></property>
      <property name="DrillThroughFilter"><![CDATA[]]></property>
      <property name="DrillThroughFrom"><![CDATA[]]></property>
      <property name="DrillThroughJoins"><![CDATA[]]></property>
      <CustomProperties>
        <Property name="ID" datatype="8"><![CDATA[f597ee89-831c-4657-8e44-a4d92b27812f]]></Property>
        <Property name="ObjectKey" datatype="8"><![CDATA[826d5da9-c9cc-4f8d-9432-d7357fda4677]]></Property>
      </CustomProperties>
      <DataSources>
        <DataSource method="Add" name="dv" ClassType="6" SubClassType="0">
          <CustomProperties>
            <Property name="ID" datatype="8"><![CDATA[af4c64e8-2b41-4fab-a1fa-acd52b27625e]]></Property>
          </CustomProperties>
        </DataSource>
      </DataSources>
      <Aggregations />
    </Partition>
    <Partition method="Add" name="Год_2007" ClassType="19" SubClassType="0" Description="" OlapMode="0" AggregationPrefix="ПоступлениявбюджетыТула_Год2007_" EstimatedRows="837775" IsReadWrite="false">
      <property name="SourceTable"><![CDATA["DV"."F_F_BUDGETINCOMINGSTULA"]]></property>
      <property name="SourceTableAlias"><![CDATA["DV"."F_F_BUDGETINCOMINGSTULA"]]></property>
      <property name="SourceTableFilter"><![CDATA["DV"."F_F_BUDGETINCOMINGSTULA"."REFYEARDAYUNV" between 20070000 and 20079999]]></property>
      <property name="FromClause"><![CDATA["DV"."F_F_BUDGETINCOMINGSTULA", "DV"."DV_KD_UFK2", "DV"."DV_OKATO_UFK2", "DV"."BV_OKATO_BRIDGE", "DV"."DV_REGIONS_UFK2", "DV"."BV_REGIONS_BRIDGE", "DV"."FX_FX_BUDGETLEVELS", "DV"."DATASOURCES", "DV"."BV_KD_BRIDGE", "DV"."BV_KD_BRIDGEPLAN", "DV"."BV_REGIONS_BRIDGEPLAN", "DV"."BV_KIF_BRIDGEPLAN", "DV"."BV_KIF_BRIDGE", "DV"."BV_KVSR_BRIDGE", "DV"."BV_PROGRAMS_BRIDGE", "DV"."D_DOC_LIST", "DV"."DV_FX_DATE_YEARDAYUNV", "DV"."FX_DATE_YEARDAYUNV"]]></property>
      <property name="JoinClause"><![CDATA[("DV"."F_F_BUDGETINCOMINGSTULA"."REFKD"="DV"."DV_KD_UFK2"."ID") AND ("DV"."F_F_BUDGETINCOMINGSTULA"."REFOKATO"="DV"."DV_OKATO_UFK2"."ID") AND ("DV"."DV_OKATO_UFK2"."REFBRIDGEOKATO"="DV"."BV_OKATO_BRIDGE"."ID") AND ("DV"."F_F_BUDGETINCOMINGSTULA"."REFREGIONS"="DV"."DV_REGIONS_UFK2"."ID") AND ("DV"."DV_REGIONS_UFK2"."REFBRIDGEREGIONS"="DV"."BV_REGIONS_BRIDGE"."ID") AND ("DV"."F_F_BUDGETINCOMINGSTULA"."REFBUDGETLEVELS"="DV"."FX_FX_BUDGETLEVELS"."ID") AND ("DV"."F_F_BUDGETINCOMINGSTULA"."SOURCEID"="DV"."DATASOURCES"."ID") AND ("DV"."DV_KD_UFK2"."REFBRIDGEKD"="DV"."BV_KD_BRIDGE"."ID") AND ("DV"."DV_KD_UFK2"."REFBRIDGEKDPLAN"="DV"."BV_KD_BRIDGEPLAN"."ID") AND ("DV"."DV_REGIONS_UFK2"."REFBRIDGEREGIONSPLAN"="DV"."BV_REGIONS_BRIDGEPLAN"."ID") AND ("DV"."DV_KD_UFK2"."REFKIFBRIDGEPLAN"="DV"."BV_KIF_BRIDGEPLAN"."ID") AND ("DV"."DV_KD_UFK2"."REFKIFBRIDGE"="DV"."BV_KIF_BRIDGE"."ID") AND ("DV"."DV_KD_UFK2"."REFKVSRBRIDGE"="DV"."BV_KVSR_BRIDGE"."ID") AND ("DV"."DV_KD_UFK2"."REFPROGRAMSBRIDGE"="DV"."BV_PROGRAMS_BRIDGE"."ID") AND ("DV"."F_F_BUDGETINCOMINGSTULA"."REFDOC"="DV"."D_DOC_LIST"."ID") AND ("DV"."F_F_BUDGETINCOMINGSTULA"."REFFKDAY"="DV"."DV_FX_DATE_YEARDAYUNV"."ID") AND ("DV"."F_F_BUDGETINCOMINGSTULA"."REFYEARDAYUNV"="DV"."FX_DATE_YEARDAYUNV"."ID")]]></property>
      <property name="DrillThroughColumns"><![CDATA[]]></property>
      <property name="DrillThroughFilter"><![CDATA[]]></property>
      <property name="DrillThroughFrom"><![CDATA[]]></property>
      <property name="DrillThroughJoins"><![CDATA[]]></property>
      <CustomProperties>
        <Property name="ID" datatype="8"><![CDATA[501e52ec-b39a-4a49-906c-a1ad18c36d72]]></Property>
        <Property name="ObjectKey" datatype="8"><![CDATA[826d5da9-c9cc-4f8d-9432-d7357fda4677]]></Property>
      </CustomProperties>
      <DataSources>
        <DataSource method="Add" name="dv" ClassType="6" SubClassType="0">
          <CustomProperties>
            <Property name="ID" datatype="8"><![CDATA[af4c64e8-2b41-4fab-a1fa-acd52b27625e]]></Property>
          </CustomProperties>
        </DataSource>
      </DataSources>
      <Aggregations />
    </Partition>
    <Partition method="Add" name="Год_2008" ClassType="19" SubClassType="0" Description="" OlapMode="0" AggregationPrefix="ПоступлениявбюджетыТула_Год2008_" EstimatedRows="837775" IsReadWrite="false">
      <property name="SourceTable"><![CDATA["DV"."F_F_BUDGETINCOMINGSTULA"]]></property>
      <property name="SourceTableAlias"><![CDATA["DV"."F_F_BUDGETINCOMINGSTULA"]]></property>
      <property name="SourceTableFilter"><![CDATA["DV"."F_F_BUDGETINCOMINGSTULA"."REFYEARDAYUNV" between 20080000 and 20089999]]></property>
      <property name="FromClause"><![CDATA["DV"."F_F_BUDGETINCOMINGSTULA", "DV"."DV_KD_UFK2", "DV"."DV_OKATO_UFK2", "DV"."BV_OKATO_BRIDGE", "DV"."DV_REGIONS_UFK2", "DV"."BV_REGIONS_BRIDGE", "DV"."FX_FX_BUDGETLEVELS", "DV"."DATASOURCES", "DV"."BV_KD_BRIDGE", "DV"."BV_KD_BRIDGEPLAN", "DV"."BV_REGIONS_BRIDGEPLAN", "DV"."BV_KIF_BRIDGEPLAN", "DV"."BV_KIF_BRIDGE", "DV"."BV_KVSR_BRIDGE", "DV"."BV_PROGRAMS_BRIDGE", "DV"."D_DOC_LIST", "DV"."DV_FX_DATE_YEARDAYUNV", "DV"."FX_DATE_YEARDAYUNV"]]></property>
      <property name="JoinClause"><![CDATA[("DV"."F_F_BUDGETINCOMINGSTULA"."REFKD"="DV"."DV_KD_UFK2"."ID") AND ("DV"."F_F_BUDGETINCOMINGSTULA"."REFOKATO"="DV"."DV_OKATO_UFK2"."ID") AND ("DV"."DV_OKATO_UFK2"."REFBRIDGEOKATO"="DV"."BV_OKATO_BRIDGE"."ID") AND ("DV"."F_F_BUDGETINCOMINGSTULA"."REFREGIONS"="DV"."DV_REGIONS_UFK2"."ID") AND ("DV"."DV_REGIONS_UFK2"."REFBRIDGEREGIONS"="DV"."BV_REGIONS_BRIDGE"."ID") AND ("DV"."F_F_BUDGETINCOMINGSTULA"."REFBUDGETLEVELS"="DV"."FX_FX_BUDGETLEVELS"."ID") AND ("DV"."F_F_BUDGETINCOMINGSTULA"."SOURCEID"="DV"."DATASOURCES"."ID") AND ("DV"."DV_KD_UFK2"."REFBRIDGEKD"="DV"."BV_KD_BRIDGE"."ID") AND ("DV"."DV_KD_UFK2"."REFBRIDGEKDPLAN"="DV"."BV_KD_BRIDGEPLAN"."ID") AND ("DV"."DV_REGIONS_UFK2"."REFBRIDGEREGIONSPLAN"="DV"."BV_REGIONS_BRIDGEPLAN"."ID") AND ("DV"."DV_KD_UFK2"."REFKIFBRIDGEPLAN"="DV"."BV_KIF_BRIDGEPLAN"."ID") AND ("DV"."DV_KD_UFK2"."REFKIFBRIDGE"="DV"."BV_KIF_BRIDGE"."ID") AND ("DV"."DV_KD_UFK2"."REFKVSRBRIDGE"="DV"."BV_KVSR_BRIDGE"."ID") AND ("DV"."DV_KD_UFK2"."REFPROGRAMSBRIDGE"="DV"."BV_PROGRAMS_BRIDGE"."ID") AND ("DV"."F_F_BUDGETINCOMINGSTULA"."REFDOC"="DV"."D_DOC_LIST"."ID") AND ("DV"."F_F_BUDGETINCOMINGSTULA"."REFFKDAY"="DV"."DV_FX_DATE_YEARDAYUNV"."ID") AND ("DV"."F_F_BUDGETINCOMINGSTULA"."REFYEARDAYUNV"="DV"."FX_DATE_YEARDAYUNV"."ID")]]></property>
      <property name="DrillThroughColumns"><![CDATA[]]></property>
      <property name="DrillThroughFilter"><![CDATA[]]></property>
      <property name="DrillThroughFrom"><![CDATA[]]></property>
      <property name="DrillThroughJoins"><![CDATA[]]></property>
      <CustomProperties>
        <Property name="ID" datatype="8"><![CDATA[a6eac1f8-23dc-449a-8b03-1994f92b9874]]></Property>
        <Property name="ObjectKey" datatype="8"><![CDATA[826d5da9-c9cc-4f8d-9432-d7357fda4677]]></Property>
      </CustomProperties>
      <DataSources>
        <DataSource method="Add" name="dv" ClassType="6" SubClassType="0">
          <CustomProperties>
            <Property name="ID" datatype="8"><![CDATA[af4c64e8-2b41-4fab-a1fa-acd52b27625e]]></Property>
          </CustomProperties>
        </DataSource>
      </DataSources>
      <Aggregations />
    </Partition>
    <Partition method="Add" name="Год_2009" ClassType="19" SubClassType="0" Description="" OlapMode="0" AggregationPrefix="ПоступлениявбюджетыТула_Год2009_" EstimatedRows="837775" IsReadWrite="false">
      <property name="SourceTable"><![CDATA["DV"."F_F_BUDGETINCOMINGSTULA"]]></property>
      <property name="SourceTableAlias"><![CDATA["DV"."F_F_BUDGETINCOMINGSTULA"]]></property>
      <property name="SourceTableFilter"><![CDATA["DV"."F_F_BUDGETINCOMINGSTULA"."REFYEARDAYUNV" between 20090000 and 20099999]]></property>
      <property name="FromClause"><![CDATA["DV"."F_F_BUDGETINCOMINGSTULA", "DV"."DV_KD_UFK2", "DV"."DV_OKATO_UFK2", "DV"."BV_OKATO_BRIDGE", "DV"."DV_REGIONS_UFK2", "DV"."BV_REGIONS_BRIDGE", "DV"."FX_FX_BUDGETLEVELS", "DV"."DATASOURCES", "DV"."BV_KD_BRIDGE", "DV"."BV_KD_BRIDGEPLAN", "DV"."BV_REGIONS_BRIDGEPLAN", "DV"."BV_KIF_BRIDGEPLAN", "DV"."BV_KIF_BRIDGE", "DV"."BV_KVSR_BRIDGE", "DV"."BV_PROGRAMS_BRIDGE", "DV"."D_DOC_LIST", "DV"."DV_FX_DATE_YEARDAYUNV", "DV"."FX_DATE_YEARDAYUNV"]]></property>
      <property name="JoinClause"><![CDATA[("DV"."F_F_BUDGETINCOMINGSTULA"."REFKD"="DV"."DV_KD_UFK2"."ID") AND ("DV"."F_F_BUDGETINCOMINGSTULA"."REFOKATO"="DV"."DV_OKATO_UFK2"."ID") AND ("DV"."DV_OKATO_UFK2"."REFBRIDGEOKATO"="DV"."BV_OKATO_BRIDGE"."ID") AND ("DV"."F_F_BUDGETINCOMINGSTULA"."REFREGIONS"="DV"."DV_REGIONS_UFK2"."ID") AND ("DV"."DV_REGIONS_UFK2"."REFBRIDGEREGIONS"="DV"."BV_REGIONS_BRIDGE"."ID") AND ("DV"."F_F_BUDGETINCOMINGSTULA"."REFBUDGETLEVELS"="DV"."FX_FX_BUDGETLEVELS"."ID") AND ("DV"."F_F_BUDGETINCOMINGSTULA"."SOURCEID"="DV"."DATASOURCES"."ID") AND ("DV"."DV_KD_UFK2"."REFBRIDGEKD"="DV"."BV_KD_BRIDGE"."ID") AND ("DV"."DV_KD_UFK2"."REFBRIDGEKDPLAN"="DV"."BV_KD_BRIDGEPLAN"."ID") AND ("DV"."DV_REGIONS_UFK2"."REFBRIDGEREGIONSPLAN"="DV"."BV_REGIONS_BRIDGEPLAN"."ID") AND ("DV"."DV_KD_UFK2"."REFKIFBRIDGEPLAN"="DV"."BV_KIF_BRIDGEPLAN"."ID") AND ("DV"."DV_KD_UFK2"."REFKIFBRIDGE"="DV"."BV_KIF_BRIDGE"."ID") AND ("DV"."DV_KD_UFK2"."REFKVSRBRIDGE"="DV"."BV_KVSR_BRIDGE"."ID") AND ("DV"."DV_KD_UFK2"."REFPROGRAMSBRIDGE"="DV"."BV_PROGRAMS_BRIDGE"."ID") AND ("DV"."F_F_BUDGETINCOMINGSTULA"."REFDOC"="DV"."D_DOC_LIST"."ID") AND ("DV"."F_F_BUDGETINCOMINGSTULA"."REFFKDAY"="DV"."DV_FX_DATE_YEARDAYUNV"."ID") AND ("DV"."F_F_BUDGETINCOMINGSTULA"."REFYEARDAYUNV"="DV"."FX_DATE_YEARDAYUNV"."ID")]]></property>
      <property name="DrillThroughColumns"><![CDATA[]]></property>
      <property name="DrillThroughFilter"><![CDATA[]]></property>
      <property name="DrillThroughFrom"><![CDATA[]]></property>
      <property name="DrillThroughJoins"><![CDATA[]]></property>
      <CustomProperties>
        <Property name="ID" datatype="8"><![CDATA[a4c7ae56-437c-4782-aa9c-f09b095129f8]]></Property>
        <Property name="ObjectKey" datatype="8"><![CDATA[826d5da9-c9cc-4f8d-9432-d7357fda4677]]></Property>
      </CustomProperties>
      <DataSources>
        <DataSource method="Add" name="dv" ClassType="6" SubClassType="0">
          <CustomProperties>
            <Property name="ID" datatype="8"><![CDATA[af4c64e8-2b41-4fab-a1fa-acd52b27625e]]></Property>
          </CustomProperties>
        </DataSource>
      </DataSources>
      <Aggregations />
    </Partition>
    <Partition method="Add" name="Год_2010" ClassType="19" SubClassType="0" Description="" OlapMode="0" AggregationPrefix="ПоступлениявбюджетыТула_Год2010_" EstimatedRows="837775" IsReadWrite="false">
      <property name="SourceTable"><![CDATA["DV"."F_F_BUDGETINCOMINGSTULA"]]></property>
      <property name="SourceTableAlias"><![CDATA["DV"."F_F_BUDGETINCOMINGSTULA"]]></property>
      <property name="SourceTableFilter"><![CDATA["DV"."F_F_BUDGETINCOMINGSTULA"."REFYEARDAYUNV" between 20100000 and 20109999]]></property>
      <property name="FromClause"><![CDATA["DV"."F_F_BUDGETINCOMINGSTULA", "DV"."DV_KD_UFK2", "DV"."DV_OKATO_UFK2", "DV"."BV_OKATO_BRIDGE", "DV"."DV_REGIONS_UFK2", "DV"."BV_REGIONS_BRIDGE", "DV"."FX_FX_BUDGETLEVELS", "DV"."DATASOURCES", "DV"."BV_KD_BRIDGE", "DV"."BV_KD_BRIDGEPLAN", "DV"."BV_REGIONS_BRIDGEPLAN", "DV"."BV_KIF_BRIDGEPLAN", "DV"."BV_KIF_BRIDGE", "DV"."BV_KVSR_BRIDGE", "DV"."BV_PROGRAMS_BRIDGE", "DV"."D_DOC_LIST", "DV"."DV_FX_DATE_YEARDAYUNV", "DV"."FX_DATE_YEARDAYUNV"]]></property>
      <property name="JoinClause"><![CDATA[("DV"."F_F_BUDGETINCOMINGSTULA"."REFKD"="DV"."DV_KD_UFK2"."ID") AND ("DV"."F_F_BUDGETINCOMINGSTULA"."REFOKATO"="DV"."DV_OKATO_UFK2"."ID") AND ("DV"."DV_OKATO_UFK2"."REFBRIDGEOKATO"="DV"."BV_OKATO_BRIDGE"."ID") AND ("DV"."F_F_BUDGETINCOMINGSTULA"."REFREGIONS"="DV"."DV_REGIONS_UFK2"."ID") AND ("DV"."DV_REGIONS_UFK2"."REFBRIDGEREGIONS"="DV"."BV_REGIONS_BRIDGE"."ID") AND ("DV"."F_F_BUDGETINCOMINGSTULA"."REFBUDGETLEVELS"="DV"."FX_FX_BUDGETLEVELS"."ID") AND ("DV"."F_F_BUDGETINCOMINGSTULA"."SOURCEID"="DV"."DATASOURCES"."ID") AND ("DV"."DV_KD_UFK2"."REFBRIDGEKD"="DV"."BV_KD_BRIDGE"."ID") AND ("DV"."DV_KD_UFK2"."REFBRIDGEKDPLAN"="DV"."BV_KD_BRIDGEPLAN"."ID") AND ("DV"."DV_REGIONS_UFK2"."REFBRIDGEREGIONSPLAN"="DV"."BV_REGIONS_BRIDGEPLAN"."ID") AND ("DV"."DV_KD_UFK2"."REFKIFBRIDGEPLAN"="DV"."BV_KIF_BRIDGEPLAN"."ID") AND ("DV"."DV_KD_UFK2"."REFKIFBRIDGE"="DV"."BV_KIF_BRIDGE"."ID") AND ("DV"."DV_KD_UFK2"."REFKVSRBRIDGE"="DV"."BV_KVSR_BRIDGE"."ID") AND ("DV"."DV_KD_UFK2"."REFPROGRAMSBRIDGE"="DV"."BV_PROGRAMS_BRIDGE"."ID") AND ("DV"."F_F_BUDGETINCOMINGSTULA"."REFDOC"="DV"."D_DOC_LIST"."ID") AND ("DV"."F_F_BUDGETINCOMINGSTULA"."REFFKDAY"="DV"."DV_FX_DATE_YEARDAYUNV"."ID") AND ("DV"."F_F_BUDGETINCOMINGSTULA"."REFYEARDAYUNV"="DV"."FX_DATE_YEARDAYUNV"."ID")]]></property>
      <property name="DrillThroughColumns"><![CDATA[]]></property>
      <property name="DrillThroughFilter"><![CDATA[]]></property>
      <property name="DrillThroughFrom"><![CDATA[]]></property>
      <property name="DrillThroughJoins"><![CDATA[]]></property>
      <CustomProperties>
        <Property name="ID" datatype="8"><![CDATA[8add11b1-9e10-40a6-84df-3a5426ce87ae]]></Property>
        <Property name="ObjectKey" datatype="8"><![CDATA[826d5da9-c9cc-4f8d-9432-d7357fda4677]]></Property>
      </CustomProperties>
      <DataSources>
        <DataSource method="Add" name="dv" ClassType="6" SubClassType="0">
          <CustomProperties>
            <Property name="ID" datatype="8"><![CDATA[af4c64e8-2b41-4fab-a1fa-acd52b27625e]]></Property>
          </CustomProperties>
        </DataSource>
      </DataSources>
      <Aggregations />
    </Partition>
    <Partition method="Add" name="Год_2011" ClassType="19" SubClassType="0" Description="" OlapMode="0" AggregationPrefix="УФК_СводФУ_Год_2011_" EstimatedRows="837775" IsReadWrite="false">
      <property name="SourceTable"><![CDATA["DV"."F_F_BUDGETINCOMINGSTULA"]]></property>
      <property name="SourceTableAlias"><![CDATA["DV"."F_F_BUDGETINCOMINGSTULA"]]></property>
      <property name="SourceTableFilter"><![CDATA["DV"."F_F_BUDGETINCOMINGSTULA"."REFYEARDAYUNV" between 20110000 and 20119999]]></property>
      <property name="FromClause"><![CDATA["DV"."F_F_BUDGETINCOMINGSTULA", "DV"."DV_KD_UFK2", "DV"."DV_OKATO_UFK2", "DV"."BV_OKATO_BRIDGE", "DV"."DV_REGIONS_UFK2", "DV"."BV_REGIONS_BRIDGE", "DV"."FX_FX_BUDGETLEVELS", "DV"."DATASOURCES", "DV"."BV_KD_BRIDGE", "DV"."BV_KD_BRIDGEPLAN", "DV"."BV_REGIONS_BRIDGEPLAN", "DV"."BV_KIF_BRIDGEPLAN", "DV"."BV_KIF_BRIDGE", "DV"."BV_KVSR_BRIDGE", "DV"."BV_PROGRAMS_BRIDGE", "DV"."D_DOC_LIST", "DV"."DV_FX_DATE_YEARDAYUNV", "DV"."FX_DATE_YEARDAYUNV"]]></property>
      <property name="JoinClause"><![CDATA[("DV"."F_F_BUDGETINCOMINGSTULA"."REFKD"="DV"."DV_KD_UFK2"."ID") AND ("DV"."F_F_BUDGETINCOMINGSTULA"."REFOKATO"="DV"."DV_OKATO_UFK2"."ID") AND ("DV"."DV_OKATO_UFK2"."REFBRIDGEOKATO"="DV"."BV_OKATO_BRIDGE"."ID") AND ("DV"."F_F_BUDGETINCOMINGSTULA"."REFREGIONS"="DV"."DV_REGIONS_UFK2"."ID") AND ("DV"."DV_REGIONS_UFK2"."REFBRIDGEREGIONS"="DV"."BV_REGIONS_BRIDGE"."ID") AND ("DV"."F_F_BUDGETINCOMINGSTULA"."REFBUDGETLEVELS"="DV"."FX_FX_BUDGETLEVELS"."ID") AND ("DV"."F_F_BUDGETINCOMINGSTULA"."SOURCEID"="DV"."DATASOURCES"."ID") AND ("DV"."DV_KD_UFK2"."REFBRIDGEKD"="DV"."BV_KD_BRIDGE"."ID") AND ("DV"."DV_KD_UFK2"."REFBRIDGEKDPLAN"="DV"."BV_KD_BRIDGEPLAN"."ID") AND ("DV"."DV_REGIONS_UFK2"."REFBRIDGEREGIONSPLAN"="DV"."BV_REGIONS_BRIDGEPLAN"."ID") AND ("DV"."DV_KD_UFK2"."REFKIFBRIDGEPLAN"="DV"."BV_KIF_BRIDGEPLAN"."ID") AND ("DV"."DV_KD_UFK2"."REFKIFBRIDGE"="DV"."BV_KIF_BRIDGE"."ID") AND ("DV"."DV_KD_UFK2"."REFKVSRBRIDGE"="DV"."BV_KVSR_BRIDGE"."ID") AND ("DV"."DV_KD_UFK2"."REFPROGRAMSBRIDGE"="DV"."BV_PROGRAMS_BRIDGE"."ID") AND ("DV"."F_F_BUDGETINCOMINGSTULA"."REFDOC"="DV"."D_DOC_LIST"."ID") AND ("DV"."F_F_BUDGETINCOMINGSTULA"."REFFKDAY"="DV"."DV_FX_DATE_YEARDAYUNV"."ID") AND ("DV"."F_F_BUDGETINCOMINGSTULA"."REFYEARDAYUNV"="DV"."FX_DATE_YEARDAYUNV"."ID")]]></property>
      <property name="DrillThroughColumns"><![CDATA[]]></property>
      <property name="DrillThroughFilter"><![CDATA[]]></property>
      <property name="DrillThroughFrom"><![CDATA[]]></property>
      <property name="DrillThroughJoins"><![CDATA[]]></property>
      <CustomProperties>
        <Property name="ID" datatype="8"><![CDATA[5372947c-3438-40e1-93b7-01a758371f76]]></Property>
        <Property name="ObjectKey" datatype="8"><![CDATA[826d5da9-c9cc-4f8d-9432-d7357fda4677]]></Property>
      </CustomProperties>
      <DataSources>
        <DataSource method="Add" name="dv" ClassType="6" SubClassType="0">
          <CustomProperties>
            <Property name="ID" datatype="8"><![CDATA[af4c64e8-2b41-4fab-a1fa-acd52b27625e]]></Property>
          </CustomProperties>
        </DataSource>
      </DataSources>
      <Aggregations />
    </Partition>
    <Partition method="Add" name="Год_2012" ClassType="19" SubClassType="0" Description="" OlapMode="0" AggregationPrefix="УФК_СводФУ_Год_2012_" EstimatedRows="837775" IsReadWrite="false">
      <property name="SourceTable"><![CDATA["DV"."F_F_BUDGETINCOMINGSTULA"]]></property>
      <property name="SourceTableAlias"><![CDATA["DV"."F_F_BUDGETINCOMINGSTULA"]]></property>
      <property name="SourceTableFilter"><![CDATA["DV"."F_F_BUDGETINCOMINGSTULA"."REFYEARDAYUNV" between 20120000 and 20129999]]></property>
      <property name="FromClause"><![CDATA["DV"."F_F_BUDGETINCOMINGSTULA", "DV"."DV_KD_UFK2", "DV"."DV_OKATO_UFK2", "DV"."BV_OKATO_BRIDGE", "DV"."DV_REGIONS_UFK2", "DV"."BV_REGIONS_BRIDGE", "DV"."FX_FX_BUDGETLEVELS", "DV"."DATASOURCES", "DV"."BV_KD_BRIDGE", "DV"."BV_KD_BRIDGEPLAN", "DV"."BV_REGIONS_BRIDGEPLAN", "DV"."BV_KIF_BRIDGEPLAN", "DV"."BV_KIF_BRIDGE", "DV"."BV_KVSR_BRIDGE", "DV"."BV_PROGRAMS_BRIDGE", "DV"."D_DOC_LIST", "DV"."DV_FX_DATE_YEARDAYUNV", "DV"."FX_DATE_YEARDAYUNV"]]></property>
      <property name="JoinClause"><![CDATA[("DV"."F_F_BUDGETINCOMINGSTULA"."REFKD"="DV"."DV_KD_UFK2"."ID") AND ("DV"."F_F_BUDGETINCOMINGSTULA"."REFOKATO"="DV"."DV_OKATO_UFK2"."ID") AND ("DV"."DV_OKATO_UFK2"."REFBRIDGEOKATO"="DV"."BV_OKATO_BRIDGE"."ID") AND ("DV"."F_F_BUDGETINCOMINGSTULA"."REFREGIONS"="DV"."DV_REGIONS_UFK2"."ID") AND ("DV"."DV_REGIONS_UFK2"."REFBRIDGEREGIONS"="DV"."BV_REGIONS_BRIDGE"."ID") AND ("DV"."F_F_BUDGETINCOMINGSTULA"."REFBUDGETLEVELS"="DV"."FX_FX_BUDGETLEVELS"."ID") AND ("DV"."F_F_BUDGETINCOMINGSTULA"."SOURCEID"="DV"."DATASOURCES"."ID") AND ("DV"."DV_KD_UFK2"."REFBRIDGEKD"="DV"."BV_KD_BRIDGE"."ID") AND ("DV"."DV_KD_UFK2"."REFBRIDGEKDPLAN"="DV"."BV_KD_BRIDGEPLAN"."ID") AND ("DV"."DV_REGIONS_UFK2"."REFBRIDGEREGIONSPLAN"="DV"."BV_REGIONS_BRIDGEPLAN"."ID") AND ("DV"."DV_KD_UFK2"."REFKIFBRIDGEPLAN"="DV"."BV_KIF_BRIDGEPLAN"."ID") AND ("DV"."DV_KD_UFK2"."REFKIFBRIDGE"="DV"."BV_KIF_BRIDGE"."ID") AND ("DV"."DV_KD_UFK2"."REFKVSRBRIDGE"="DV"."BV_KVSR_BRIDGE"."ID") AND ("DV"."DV_KD_UFK2"."REFPROGRAMSBRIDGE"="DV"."BV_PROGRAMS_BRIDGE"."ID") AND ("DV"."F_F_BUDGETINCOMINGSTULA"."REFDOC"="DV"."D_DOC_LIST"."ID") AND ("DV"."F_F_BUDGETINCOMINGSTULA"."REFFKDAY"="DV"."DV_FX_DATE_YEARDAYUNV"."ID") AND ("DV"."F_F_BUDGETINCOMINGSTULA"."REFYEARDAYUNV"="DV"."FX_DATE_YEARDAYUNV"."ID")]]></property>
      <property name="DrillThroughColumns"><![CDATA[]]></property>
      <property name="DrillThroughFilter"><![CDATA[]]></property>
      <property name="DrillThroughFrom"><![CDATA[]]></property>
      <property name="DrillThroughJoins"><![CDATA[]]></property>
      <CustomProperties>
        <Property name="ID" datatype="8"><![CDATA[f637961c-abc9-427c-b1de-e17dedb95d97]]></Property>
        <Property name="ObjectKey" datatype="8"><![CDATA[826d5da9-c9cc-4f8d-9432-d7357fda4677]]></Property>
      </CustomProperties>
      <DataSources>
        <DataSource method="Add" name="dv" ClassType="6" SubClassType="0">
          <CustomProperties>
            <Property name="ID" datatype="8"><![CDATA[af4c64e8-2b41-4fab-a1fa-acd52b27625e]]></Property>
          </CustomProperties>
        </DataSource>
      </DataSources>
      <Aggregations />
    </Partition>
    <Partition method="Add" name="Год_2013_2020" ClassType="19" SubClassType="0" Description="" OlapMode="0" AggregationPrefix="УФК_СводФУ_Год_2013_2020_" EstimatedRows="837775" IsReadWrite="false">
      <property name="SourceTable"><![CDATA["DV"."F_F_BUDGETINCOMINGSTULA"]]></property>
      <property name="SourceTableAlias"><![CDATA["DV"."F_F_BUDGETINCOMINGSTULA"]]></property>
      <property name="SourceTableFilter"><![CDATA["DV"."F_F_BUDGETINCOMINGSTULA"."REFYEARDAYUNV" between 20130000 and 20209999]]></property>
      <property name="FromClause"><![CDATA["DV"."F_F_BUDGETINCOMINGSTULA", "DV"."DV_KD_UFK2", "DV"."DV_OKATO_UFK2", "DV"."BV_OKATO_BRIDGE", "DV"."DV_REGIONS_UFK2", "DV"."BV_REGIONS_BRIDGE", "DV"."FX_FX_BUDGETLEVELS", "DV"."DATASOURCES", "DV"."BV_KD_BRIDGE", "DV"."BV_KD_BRIDGEPLAN", "DV"."BV_REGIONS_BRIDGEPLAN", "DV"."BV_KIF_BRIDGEPLAN", "DV"."BV_KIF_BRIDGE", "DV"."BV_KVSR_BRIDGE", "DV"."BV_PROGRAMS_BRIDGE", "DV"."D_DOC_LIST", "DV"."DV_FX_DATE_YEARDAYUNV", "DV"."FX_DATE_YEARDAYUNV"]]></property>
      <property name="JoinClause"><![CDATA[("DV"."F_F_BUDGETINCOMINGSTULA"."REFKD"="DV"."DV_KD_UFK2"."ID") AND ("DV"."F_F_BUDGETINCOMINGSTULA"."REFOKATO"="DV"."DV_OKATO_UFK2"."ID") AND ("DV"."DV_OKATO_UFK2"."REFBRIDGEOKATO"="DV"."BV_OKATO_BRIDGE"."ID") AND ("DV"."F_F_BUDGETINCOMINGSTULA"."REFREGIONS"="DV"."DV_REGIONS_UFK2"."ID") AND ("DV"."DV_REGIONS_UFK2"."REFBRIDGEREGIONS"="DV"."BV_REGIONS_BRIDGE"."ID") AND ("DV"."F_F_BUDGETINCOMINGSTULA"."REFBUDGETLEVELS"="DV"."FX_FX_BUDGETLEVELS"."ID") AND ("DV"."F_F_BUDGETINCOMINGSTULA"."SOURCEID"="DV"."DATASOURCES"."ID") AND ("DV"."DV_KD_UFK2"."REFBRIDGEKD"="DV"."BV_KD_BRIDGE"."ID") AND ("DV"."DV_KD_UFK2"."REFBRIDGEKDPLAN"="DV"."BV_KD_BRIDGEPLAN"."ID") AND ("DV"."DV_REGIONS_UFK2"."REFBRIDGEREGIONSPLAN"="DV"."BV_REGIONS_BRIDGEPLAN"."ID") AND ("DV"."DV_KD_UFK2"."REFKIFBRIDGEPLAN"="DV"."BV_KIF_BRIDGEPLAN"."ID") AND ("DV"."DV_KD_UFK2"."REFKIFBRIDGE"="DV"."BV_KIF_BRIDGE"."ID") AND ("DV"."DV_KD_UFK2"."REFKVSRBRIDGE"="DV"."BV_KVSR_BRIDGE"."ID") AND ("DV"."DV_KD_UFK2"."REFPROGRAMSBRIDGE"="DV"."BV_PROGRAMS_BRIDGE"."ID") AND ("DV"."F_F_BUDGETINCOMINGSTULA"."REFDOC"="DV"."D_DOC_LIST"."ID") AND ("DV"."F_F_BUDGETINCOMINGSTULA"."REFFKDAY"="DV"."DV_FX_DATE_YEARDAYUNV"."ID") AND ("DV"."F_F_BUDGETINCOMINGSTULA"."REFYEARDAYUNV"="DV"."FX_DATE_YEARDAYUNV"."ID")]]></property>
      <property name="DrillThroughColumns"><![CDATA[]]></property>
      <property name="DrillThroughFilter"><![CDATA[]]></property>
      <property name="DrillThroughFrom"><![CDATA[]]></property>
      <property name="DrillThroughJoins"><![CDATA[]]></property>
      <CustomProperties>
        <Property name="ID" datatype="8"><![CDATA[ff043b81-95d7-43dd-937d-8f8044ed676d]]></Property>
        <Property name="ObjectKey" datatype="8"><![CDATA[826d5da9-c9cc-4f8d-9432-d7357fda4677]]></Property>
      </CustomProperties>
      <DataSources>
        <DataSource method="Add" name="dv" ClassType="6" SubClassType="0">
          <CustomProperties>
            <Property name="ID" datatype="8"><![CDATA[af4c64e8-2b41-4fab-a1fa-acd52b27625e]]></Property>
          </CustomProperties>
        </DataSource>
      </DataSources>
      <Aggregations />
    </Partition>
  </Partitions>
</Cube>