<?xml version="1.0" encoding="utf-8"?>
<Cube method="Add" name="ФО_Проект ИФ" ClassType="9" SubClassType="0" Description="Проект источников финансирования дефицита бюджета (внутренних и внешних) в разрезе алгоритмов." DataSource="dv" OlapMode="0" DefaultMeasure="" AggregationPrefix="" EstimatedRows="1" IsVisible="true" ProcessOptimizationMode="0" ProcessingKeyErrorLimit="0" AllowDrillThrough="false" FactTableSize="1">
  <property name="SourceTable"><![CDATA["DV"."F_S_PROJECT"]]></property>
  <property name="SourceTableAlias"><![CDATA["DV"."F_S_PROJECT"]]></property>
  <property name="SourceTableFilter"><![CDATA[]]></property>
  <property name="Where"><![CDATA[]]></property>
  <property name="FromClause"><![CDATA["DV"."F_S_PROJECT", "DV"."DV_REGIONS_PLAN", "DV"."DV_KIF_PLAN", "DV"."D_ALGORITHM_PLAN", "DV"."BV_KIF_BRIDGEPLAN", "DV"."BV_KIF_BRIDGE", "DV"."BV_REGIONS_BRIDGE", "DV"."BV_REGIONS_BRIDGEPLAN", "DV"."FX_FX_BUDGETLEVELS", "DV"."DATASOURCES", "DV"."DV_KVSR_PLAN", "DV"."BV_KVSR_BRIDGE", "DV"."BV_KVSR_BRIDGEPLAN", "DV"."FX_DATE_YEARDAYUNV", "DV"."D_VARIANT_BORROW"]]></property>
  <property name="JoinClause"><![CDATA[("DV"."F_S_PROJECT"."REFREGIONS"="DV"."DV_REGIONS_PLAN"."ID") AND ("DV"."F_S_PROJECT"."REFKIF"="DV"."DV_KIF_PLAN"."ID") AND ("DV"."F_S_PROJECT"."REFALGORITHM"="DV"."D_ALGORITHM_PLAN"."ID") AND ("DV"."DV_KIF_PLAN"."REFPLANBRIDGE"="DV"."BV_KIF_BRIDGEPLAN"."ID") AND ("DV"."DV_KIF_PLAN"."REFBRIDGE"="DV"."BV_KIF_BRIDGE"."ID") AND ("DV"."DV_REGIONS_PLAN"."REFBRIDGE"="DV"."BV_REGIONS_BRIDGE"."ID") AND ("DV"."DV_REGIONS_PLAN"."REFBRIDGEREGIONSPLAN"="DV"."BV_REGIONS_BRIDGEPLAN"."ID") AND ("DV"."F_S_PROJECT"."REFBUDGETLEVELS"="DV"."FX_FX_BUDGETLEVELS"."ID") AND ("DV"."F_S_PROJECT"."SOURCEID"="DV"."DATASOURCES"."ID") AND ("DV"."F_S_PROJECT"."REFKVSR"="DV"."DV_KVSR_PLAN"."ID") AND ("DV"."DV_KVSR_PLAN"."REFBRIDGE"="DV"."BV_KVSR_BRIDGE"."ID") AND ("DV"."DV_KVSR_PLAN"."REFPLANBRIDGE"="DV"."BV_KVSR_BRIDGEPLAN"."ID") AND ("DV"."F_S_PROJECT"."REFYEARDAYUNV"="DV"."FX_DATE_YEARDAYUNV"."ID") AND ("DV"."F_S_PROJECT"."REFSVARIANT"="DV"."D_VARIANT_BORROW"."ID")]]></property>
  <property name="ProcessingKeyErrorLogFileName"><![CDATA[]]></property>
  <property name="DrillThroughColumns"><![CDATA[]]></property>
  <property name="DrillThroughFrom"><![CDATA[]]></property>
  <property name="DrillThroughJoins"><![CDATA[]]></property>
  <property name="DrillThroughFilter"><![CDATA[]]></property>
  <property name="FactTable"><![CDATA["DV"."F_S_PROJECT"]]></property>
  <CustomProperties>
    <Property name="FullName" datatype="8"><![CDATA[f.S.Project]]></Property>
    <Property name="SchemaLayout" datatype="0"><![CDATA[({dv}{DV.D_ALGORITHM_PLAN}{DV.D_ALGORITHM_PLAN}{1592}{5074}{2352}{1000}{1})({dv}{DV.FX_FX_BUDGETLEVELS}{DV.FX_FX_BUDGETLEVELS}{228}{5292}{2568}{952}{1})({dv}{DV.DV_REGIONS_PLAN}{DV.DV_REGIONS_PLAN}{2790}{5025}{2328}{940}{1})({dv}{DV.BV_REGIONS_BRIDGE}{DV.BV_REGIONS_BRIDGE}{1665}{8310}{2388}{1024}{1})({dv}{DV.BV_REGIONS_BRIDGEPLAN}{DV.BV_REGIONS_BRIDGEPLAN}{3090}{8340}{2463}{940}{1})({dv}{DV.DV_KIF_PLAN}{DV.DV_KIF_PLAN}{4712}{4999}{1935}{961}{1})({dv}{DV.BV_KIF_BRIDGE}{DV.BV_KIF_BRIDGE}{4380}{8430}{1668}{904}{1})({dv}{DV.BV_KIF_BRIDGEPLAN}{DV.BV_KIF_BRIDGEPLAN}{5490}{8490}{2412}{1084}{1})({dv}{DV.F_S_PROJECT}{DV.F_S_PROJECT}{1644}{276}{2010}{3431}{1})({dv}{DV.DATASOURCES}{DV.DATASOURCES}{180}{348}{2028}{940}{1})({dv}{DV.DV_KVSR_PLAN}{DV.DV_KVSR_PLAN}{6660}{4995}{1890}{925}{1})({dv}{DV.BV_KVSR_BRIDGE}{DV.BV_KVSR_BRIDGE}{6825}{8520}{1875}{910}{1})({dv}{DV.BV_KVSR_BRIDGEPLAN}{DV.BV_KVSR_BRIDGEPLAN}{7920}{8205}{2295}{955}{1})({dv}{DV.FX_DATE_YEARDAYUNV}{DV.FX_DATE_YEARDAYUNV}{8085}{1230}{2265}{910}{1})({dv}{DV.D_VARIANT_BORROW}{DV.D_VARIANT_BORROW}{8205}{4725}{2340}{910}{1})]]></Property>
    <Property name="SubClass" datatype="8"><![CDATA[ВВОД]]></Property>
    <Property name="SchemaJoins" datatype="0"><![CDATA[("DV"."F_S_PROJECT"."REFREGIONS"="DV"."DV_REGIONS_PLAN"."ID") AND ("DV"."F_S_PROJECT"."REFKIF"="DV"."DV_KIF_PLAN"."ID") AND ("DV"."F_S_PROJECT"."REFALGORITHM"="DV"."D_ALGORITHM_PLAN"."ID") AND ("DV"."DV_KIF_PLAN"."REFPLANBRIDGE"="DV"."BV_KIF_BRIDGEPLAN"."ID") AND ("DV"."DV_KIF_PLAN"."REFBRIDGE"="DV"."BV_KIF_BRIDGE"."ID") AND ("DV"."DV_REGIONS_PLAN"."REFBRIDGE"="DV"."BV_REGIONS_BRIDGE"."ID") AND ("DV"."DV_REGIONS_PLAN"."REFBRIDGEREGIONSPLAN"="DV"."BV_REGIONS_BRIDGEPLAN"."ID") AND ("DV"."F_S_PROJECT"."REFBUDGETLEVELS"="DV"."FX_FX_BUDGETLEVELS"."ID") AND ("DV"."F_S_PROJECT"."SOURCEID"="DV"."DATASOURCES"."ID") AND ("DV"."F_S_PROJECT"."REFKVSR"="DV"."DV_KVSR_PLAN"."ID") AND ("DV"."DV_KVSR_PLAN"."REFBRIDGE"="DV"."BV_KVSR_BRIDGE"."ID") AND ("DV"."DV_KVSR_PLAN"."REFPLANBRIDGE"="DV"."BV_KVSR_BRIDGEPLAN"."ID") AND ("DV"."F_S_PROJECT"."REFYEARDAYUNV"="DV"."FX_DATE_YEARDAYUNV"."ID") AND ("DV"."F_S_PROJECT"."REFSVARIANT"="DV"."D_VARIANT_BORROW"."ID")]]></Property>
    <Property name="ID" datatype="8"><![CDATA[a1d46303-1910-494f-8664-090bae394faf]]></Property>
    <Property name="MeasureGroupID" datatype="8"><![CDATA[5797ae6f-777e-4da2-bfa8-767bd2c562a4]]></Property>
    <Property name="ObjectKey" datatype="8"><![CDATA[798bcb1c-423f-40ee-a746-0125eae93c0c]]></Property>
  </CustomProperties>
  <DataSources>
    <DataSource method="Add" name="dv" ClassType="6" SubClassType="0">
      <CustomProperties>
        <Property name="ID" datatype="8"><![CDATA[af4c64e8-2b41-4fab-a1fa-acd52b27625e]]></Property>
      </CustomProperties>
    </DataSource>
  </DataSources>
  <CubeDimensions>
    <CubeDimension method="Add" name="Алгоритм.Проект бюджета" ClassType="11" SubClassType="0" AggregationUsage="0" IsVisible="true" Num="1">
      <CubeLevels>
        <CubeLevel method="Update" name="(All)" ClassType="12" SubClassType="0" EnableAggregations="true" IsDisabled="false" IsVisible="true">
          <property name="CustomRollUpExpression"><![CDATA[]]></property>
          <property name="MemberKeyColumn"><![CDATA[Все]]></property>
        </CubeLevel>
        <CubeLevel method="Update" name="КБК" ClassType="12" SubClassType="0" EnableAggregations="true" IsDisabled="false" IsVisible="true">
          <property name="CustomRollUpExpression"><![CDATA[]]></property>
          <property name="MemberKeyColumn"><![CDATA["DV"."D_ALGORITHM_PLAN"."KBK"]]></property>
        </CubeLevel>
        <CubeLevel method="Update" name="Алгоритм" ClassType="12" SubClassType="0" EnableAggregations="true" IsDisabled="false" IsVisible="true">
          <property name="CustomRollUpExpression"><![CDATA[]]></property>
          <property name="MemberKeyColumn"><![CDATA["DV"."D_ALGORITHM_PLAN"."CODE"]]></property>
        </CubeLevel>
      </CubeLevels>
    </CubeDimension>
    <CubeDimension method="Add" name="Уровни бюджетов" ClassType="11" SubClassType="2" AggregationUsage="0" IsVisible="true" Num="2">
      <CubeLevels>
        <CubeLevel method="Update" name="(All)" ClassType="12" SubClassType="0" EnableAggregations="true" IsDisabled="false" IsVisible="true">
          <property name="CustomRollUpExpression"><![CDATA[]]></property>
          <property name="MemberKeyColumn"><![CDATA[Все]]></property>
        </CubeLevel>
        <CubeLevel method="Update" name="Уровень бюджета" ClassType="12" SubClassType="2" EnableAggregations="true" IsVisible="true">
          <property name="CustomRollUpExpression"><![CDATA[]]></property>
          <property name="MemberKeyColumn"><![CDATA["DV"."FX_FX_BUDGETLEVELS"."ID"]]></property>
        </CubeLevel>
      </CubeLevels>
    </CubeDimension>
    <CubeDimension method="Add" name="Районы.Сопоставимый" ClassType="11" SubClassType="2" AggregationUsage="0" IsVisible="true" Num="3">
      <CubeLevels>
        <CubeLevel method="Update" name="(All)" ClassType="12" SubClassType="0" EnableAggregations="true" IsDisabled="false" IsVisible="true">
          <property name="CustomRollUpExpression"><![CDATA[]]></property>
          <property name="MemberKeyColumn"><![CDATA[Все районы]]></property>
        </CubeLevel>
        <CubeLevel method="Update" name="Район" ClassType="12" SubClassType="2" EnableAggregations="true" IsVisible="true">
          <property name="CustomRollUpExpression"><![CDATA[]]></property>
          <property name="MemberKeyColumn"><![CDATA["DV"."BV_REGIONS_BRIDGE"."ID"]]></property>
        </CubeLevel>
      </CubeLevels>
    </CubeDimension>
    <CubeDimension method="Add" name="Районы.Сопоставимый План" ClassType="11" SubClassType="2" AggregationUsage="0" IsVisible="true" Num="4">
      <CubeLevels>
        <CubeLevel method="Update" name="(All)" ClassType="12" SubClassType="0" EnableAggregations="true" IsDisabled="false" IsVisible="true">
          <property name="CustomRollUpExpression"><![CDATA[]]></property>
          <property name="MemberKeyColumn"><![CDATA[Все районы]]></property>
        </CubeLevel>
        <CubeLevel method="Update" name="Район" ClassType="12" SubClassType="2" EnableAggregations="true" IsVisible="true">
          <property name="CustomRollUpExpression"><![CDATA[]]></property>
          <property name="MemberKeyColumn"><![CDATA["DV"."BV_REGIONS_BRIDGEPLAN"."ID"]]></property>
        </CubeLevel>
      </CubeLevels>
    </CubeDimension>
    <CubeDimension method="Add" name="Районы.Планирование" ClassType="11" SubClassType="2" AggregationUsage="0" IsVisible="true" Num="5">
      <CubeLevels>
        <CubeLevel method="Update" name="(All)" ClassType="12" SubClassType="0" EnableAggregations="true" IsDisabled="false" IsVisible="true">
          <property name="CustomRollUpExpression"><![CDATA[]]></property>
          <property name="MemberKeyColumn"><![CDATA[Данные всех источников]]></property>
        </CubeLevel>
        <CubeLevel method="Update" name="Район" ClassType="12" SubClassType="2" EnableAggregations="true" IsVisible="true">
          <property name="CustomRollUpExpression"><![CDATA[]]></property>
          <property name="MemberKeyColumn"><![CDATA["DV"."DV_REGIONS_PLAN"."ID"]]></property>
        </CubeLevel>
      </CubeLevels>
    </CubeDimension>
    <CubeDimension method="Add" name="КИФ.Планирование" ClassType="11" SubClassType="2" AggregationUsage="0" IsVisible="true" Num="6">
      <CubeLevels>
        <CubeLevel method="Update" name="(All)" ClassType="12" SubClassType="0" EnableAggregations="true" IsDisabled="false" IsVisible="true">
          <property name="CustomRollUpExpression"><![CDATA[]]></property>
          <property name="MemberKeyColumn"><![CDATA[Данные всех источников]]></property>
        </CubeLevel>
        <CubeLevel method="Update" name="Источник финансирования" ClassType="12" SubClassType="2" EnableAggregations="true" IsVisible="true">
          <property name="CustomRollUpExpression"><![CDATA[]]></property>
          <property name="MemberKeyColumn"><![CDATA["DV"."DV_KIF_PLAN"."ID"]]></property>
        </CubeLevel>
      </CubeLevels>
    </CubeDimension>
    <CubeDimension method="Add" name="КИФ.Сопоставимый" ClassType="11" SubClassType="2" AggregationUsage="0" IsVisible="true" Num="7">
      <CubeLevels>
        <CubeLevel method="Update" name="(All)" ClassType="12" SubClassType="0" EnableAggregations="true" IsDisabled="false" IsVisible="true">
          <property name="CustomRollUpExpression"><![CDATA[]]></property>
          <property name="MemberKeyColumn"><![CDATA[Все источники финансирования]]></property>
        </CubeLevel>
        <CubeLevel method="Update" name="Источники финансирования" ClassType="12" SubClassType="2" EnableAggregations="true" IsVisible="true">
          <property name="CustomRollUpExpression"><![CDATA[]]></property>
          <property name="MemberKeyColumn"><![CDATA["DV"."BV_KIF_BRIDGE"."ID"]]></property>
        </CubeLevel>
      </CubeLevels>
    </CubeDimension>
    <CubeDimension method="Add" name="КИФ.Сопоставимый планирование" ClassType="11" SubClassType="2" AggregationUsage="0" IsVisible="true" Num="8">
      <CubeLevels>
        <CubeLevel method="Update" name="(All)" ClassType="12" SubClassType="0" EnableAggregations="true" IsDisabled="false" IsVisible="true">
          <property name="CustomRollUpExpression"><![CDATA[]]></property>
          <property name="MemberKeyColumn"><![CDATA[Все источники финансирования]]></property>
        </CubeLevel>
        <CubeLevel method="Update" name="Источник финансирования" ClassType="12" SubClassType="2" EnableAggregations="true" IsVisible="true">
          <property name="CustomRollUpExpression"><![CDATA[IIF(not IsLeaf([КИФ].[Сопоставимый планирование].CurrentMember) and [КИФ].[Сопоставимый планирование].CurrentMember.Properties("Направление") = "0",
Sum(Filter([КИФ].[Сопоставимый планирование].CurrentMember.Children, [КИФ].[Сопоставимый планирование].CurrentMember.Properties("Направление") = "0")) +
Sum(Filter([КИФ].[Сопоставимый планирование].CurrentMember.Children, [КИФ].[Сопоставимый планирование].CurrentMember.Properties("Направление") = "1")) -
Sum(Filter([КИФ].[Сопоставимый планирование].CurrentMember.Children, [КИФ].[Сопоставимый планирование].CurrentMember.Properties("Направление") = "-1")),
CalculationPassValue([КИФ].[Сопоставимый планирование].CurrentMember, 0))]]></property>
          <property name="MemberKeyColumn"><![CDATA["DV"."BV_KIF_BRIDGEPLAN"."ID"]]></property>
        </CubeLevel>
      </CubeLevels>
    </CubeDimension>
    <CubeDimension method="Add" name="Источники данных" ClassType="11" SubClassType="0" AggregationUsage="0" IsVisible="true" Num="9">
      <CubeLevels>
        <CubeLevel method="Update" name="(All)" ClassType="12" SubClassType="0" EnableAggregations="true" IsDisabled="false" IsVisible="true">
          <property name="CustomRollUpExpression"><![CDATA[]]></property>
          <property name="MemberKeyColumn"><![CDATA[Все источники данных]]></property>
        </CubeLevel>
        <CubeLevel method="Update" name="Источник" ClassType="12" SubClassType="0" EnableAggregations="true" IsDisabled="false" IsVisible="true">
          <property name="CustomRollUpExpression"><![CDATA[]]></property>
          <property name="MemberKeyColumn"><![CDATA["DV"."DATASOURCES"."ID"]]></property>
        </CubeLevel>
      </CubeLevels>
    </CubeDimension>
    <CubeDimension method="Add" name="Вариант.ИФ" ClassType="11" SubClassType="0" AggregationUsage="0" IsVisible="true" Num="10">
      <CubeLevels>
        <CubeLevel method="Update" name="(All)" ClassType="12" SubClassType="0" EnableAggregations="true" IsDisabled="false" IsVisible="true">
          <property name="CustomRollUpExpression"><![CDATA[]]></property>
          <property name="MemberKeyColumn"><![CDATA[Все]]></property>
        </CubeLevel>
        <CubeLevel method="Update" name="Вариант" ClassType="12" SubClassType="0" EnableAggregations="true" IsDisabled="false" IsVisible="true">
          <property name="CustomRollUpExpression"><![CDATA[]]></property>
          <property name="MemberKeyColumn"><![CDATA["DV"."D_VARIANT_BORROW"."ID"]]></property>
        </CubeLevel>
      </CubeLevels>
    </CubeDimension>
    <CubeDimension method="Add" name="Период.Период" ClassType="11" SubClassType="0" AggregationUsage="0" IsVisible="true" Num="11">
      <CubeLevels>
        <CubeLevel method="Update" name="(All)" ClassType="12" SubClassType="0" EnableAggregations="true" IsDisabled="false" IsVisible="true">
          <property name="CustomRollUpExpression"><![CDATA[]]></property>
          <property name="MemberKeyColumn"><![CDATA[Данные всех периодов]]></property>
        </CubeLevel>
        <CubeLevel method="Update" name="Год" ClassType="12" SubClassType="0" EnableAggregations="true" IsDisabled="false" IsVisible="true">
          <property name="CustomRollUpExpression"><![CDATA[]]></property>
          <property name="MemberKeyColumn"><![CDATA["DV"."FX_DATE_YEARDAYUNV"."DATEYEARID"]]></property>
        </CubeLevel>
        <CubeLevel method="Update" name="Полугодие" ClassType="12" SubClassType="0" EnableAggregations="true" IsDisabled="false" IsVisible="true">
          <property name="CustomRollUpExpression"><![CDATA[]]></property>
          <property name="MemberKeyColumn"><![CDATA["DV"."FX_DATE_YEARDAYUNV"."DATEHALFYEARID"]]></property>
        </CubeLevel>
        <CubeLevel method="Update" name="Квартал" ClassType="12" SubClassType="0" EnableAggregations="true" IsDisabled="false" IsVisible="true">
          <property name="CustomRollUpExpression"><![CDATA[]]></property>
          <property name="MemberKeyColumn"><![CDATA["DV"."FX_DATE_YEARDAYUNV"."DATEQUARTERID"]]></property>
        </CubeLevel>
        <CubeLevel method="Update" name="Месяц" ClassType="12" SubClassType="0" EnableAggregations="true" IsDisabled="false" IsVisible="true">
          <property name="CustomRollUpExpression"><![CDATA[]]></property>
          <property name="MemberKeyColumn"><![CDATA["DV"."FX_DATE_YEARDAYUNV"."DATEMONTHID"]]></property>
        </CubeLevel>
        <CubeLevel method="Update" name="День" ClassType="12" SubClassType="0" EnableAggregations="true" IsDisabled="false" IsVisible="true">
          <property name="CustomRollUpExpression"><![CDATA[]]></property>
          <property name="MemberKeyColumn"><![CDATA["DV"."FX_DATE_YEARDAYUNV"."ID"]]></property>
        </CubeLevel>
      </CubeLevels>
    </CubeDimension>
    <CubeDimension method="Add" name="Администратор.Сопоставим" ClassType="11" SubClassType="0" AggregationUsage="0" IsVisible="true" Num="12">
      <CubeLevels>
        <CubeLevel method="Update" name="(All)" ClassType="12" SubClassType="0" EnableAggregations="true" IsDisabled="false" IsVisible="true">
          <property name="CustomRollUpExpression"><![CDATA[]]></property>
          <property name="MemberKeyColumn"><![CDATA[Все администраторы]]></property>
        </CubeLevel>
        <CubeLevel method="Update" name="Администратор" ClassType="12" SubClassType="0" EnableAggregations="true" IsDisabled="false" IsVisible="true">
          <property name="CustomRollUpExpression"><![CDATA[]]></property>
          <property name="MemberKeyColumn"><![CDATA["DV"."BV_KVSR_BRIDGE"."ID"]]></property>
        </CubeLevel>
      </CubeLevels>
    </CubeDimension>
    <CubeDimension method="Add" name="Администратор.Планир" ClassType="11" SubClassType="0" AggregationUsage="0" IsVisible="true" Num="13">
      <CubeLevels>
        <CubeLevel method="Update" name="(All)" ClassType="12" SubClassType="0" EnableAggregations="true" IsDisabled="false" IsVisible="true">
          <property name="CustomRollUpExpression"><![CDATA[]]></property>
          <property name="MemberKeyColumn"><![CDATA[Данные всех источников]]></property>
        </CubeLevel>
        <CubeLevel method="Update" name="Источник" ClassType="12" SubClassType="0" EnableAggregations="true" IsDisabled="false" IsVisible="true">
          <property name="CustomRollUpExpression"><![CDATA[]]></property>
          <property name="MemberKeyColumn"><![CDATA["DV"."DV_KVSR_PLAN"."SOURCEID"]]></property>
        </CubeLevel>
        <CubeLevel method="Update" name="Администратор" ClassType="12" SubClassType="0" EnableAggregations="true" IsDisabled="false" IsVisible="true">
          <property name="CustomRollUpExpression"><![CDATA[]]></property>
          <property name="MemberKeyColumn"><![CDATA["DV"."DV_KVSR_PLAN"."ID"]]></property>
        </CubeLevel>
      </CubeLevels>
    </CubeDimension>
    <CubeDimension method="Add" name="Администратор.СопостПлан" ClassType="11" SubClassType="0" AggregationUsage="0" IsVisible="true" Num="14">
      <CubeLevels>
        <CubeLevel method="Update" name="(All)" ClassType="12" SubClassType="0" EnableAggregations="true" IsDisabled="false" IsVisible="true">
          <property name="CustomRollUpExpression"><![CDATA[]]></property>
          <property name="MemberKeyColumn"><![CDATA[Все администраторы]]></property>
        </CubeLevel>
        <CubeLevel method="Update" name="Администратор" ClassType="12" SubClassType="0" EnableAggregations="true" IsDisabled="false" IsVisible="true">
          <property name="CustomRollUpExpression"><![CDATA[]]></property>
          <property name="MemberKeyColumn"><![CDATA["DV"."BV_KVSR_BRIDGEPLAN"."ID"]]></property>
        </CubeLevel>
      </CubeLevels>
    </CubeDimension>
  </CubeDimensions>
  <CubeMeasures>
    <CubeMeasure method="Add" name="Оценка" ClassType="10" SubClassType="0" Description="Ожидаемый объем источников финансирования в текущем году" IsVisible="true" SourceColumnType="5" AggregateFunction="0" FormatString="Currency" Num="1">
      <property name="SourceColumn"><![CDATA["DV"."F_S_PROJECT"."ESTIMATE"]]></property>
    </CubeMeasure>
    <CubeMeasure method="Add" name="Прогноз" ClassType="10" SubClassType="0" Description="Прогнозируемый объем источников финансирования в очередном финансовом году и плановом периоде" IsVisible="true" SourceColumnType="5" AggregateFunction="0" FormatString="Currency" Num="2">
      <property name="SourceColumn"><![CDATA["DV"."F_S_PROJECT"."FORECAST"]]></property>
    </CubeMeasure>
  </CubeMeasures>
  <CubeRoles />
  <CubeCommands />
  <Partitions>
    <Partition method="Add" name="ФО_Проект ИФ" ClassType="19" SubClassType="0" Description="" OlapMode="0" AggregationPrefix="ФО_ПроектИФ_ФО_ПроектИФ_" EstimatedRows="1" IsReadWrite="false">
      <property name="SourceTable"><![CDATA["DV"."F_S_PROJECT"]]></property>
      <property name="SourceTableAlias"><![CDATA["DV"."F_S_PROJECT"]]></property>
      <property name="SourceTableFilter"><![CDATA[]]></property>
      <property name="FromClause"><![CDATA["DV"."F_S_PROJECT", "DV"."DV_REGIONS_PLAN", "DV"."DV_KIF_PLAN", "DV"."D_ALGORITHM_PLAN", "DV"."BV_KIF_BRIDGEPLAN", "DV"."BV_KIF_BRIDGE", "DV"."BV_REGIONS_BRIDGE", "DV"."BV_REGIONS_BRIDGEPLAN", "DV"."FX_FX_BUDGETLEVELS", "DV"."DATASOURCES", "DV"."DV_KVSR_PLAN", "DV"."BV_KVSR_BRIDGE", "DV"."BV_KVSR_BRIDGEPLAN", "DV"."FX_DATE_YEARDAYUNV", "DV"."D_VARIANT_BORROW"]]></property>
      <property name="JoinClause"><![CDATA[("DV"."F_S_PROJECT"."REFREGIONS"="DV"."DV_REGIONS_PLAN"."ID") AND ("DV"."F_S_PROJECT"."REFKIF"="DV"."DV_KIF_PLAN"."ID") AND ("DV"."F_S_PROJECT"."REFALGORITHM"="DV"."D_ALGORITHM_PLAN"."ID") AND ("DV"."DV_KIF_PLAN"."REFPLANBRIDGE"="DV"."BV_KIF_BRIDGEPLAN"."ID") AND ("DV"."DV_KIF_PLAN"."REFBRIDGE"="DV"."BV_KIF_BRIDGE"."ID") AND ("DV"."DV_REGIONS_PLAN"."REFBRIDGE"="DV"."BV_REGIONS_BRIDGE"."ID") AND ("DV"."DV_REGIONS_PLAN"."REFBRIDGEREGIONSPLAN"="DV"."BV_REGIONS_BRIDGEPLAN"."ID") AND ("DV"."F_S_PROJECT"."REFBUDGETLEVELS"="DV"."FX_FX_BUDGETLEVELS"."ID") AND ("DV"."F_S_PROJECT"."SOURCEID"="DV"."DATASOURCES"."ID") AND ("DV"."F_S_PROJECT"."REFKVSR"="DV"."DV_KVSR_PLAN"."ID") AND ("DV"."DV_KVSR_PLAN"."REFBRIDGE"="DV"."BV_KVSR_BRIDGE"."ID") AND ("DV"."DV_KVSR_PLAN"."REFPLANBRIDGE"="DV"."BV_KVSR_BRIDGEPLAN"."ID") AND ("DV"."F_S_PROJECT"."REFYEARDAYUNV"="DV"."FX_DATE_YEARDAYUNV"."ID") AND ("DV"."F_S_PROJECT"."REFSVARIANT"="DV"."D_VARIANT_BORROW"."ID")]]></property>
      <property name="DrillThroughColumns"><![CDATA[]]></property>
      <property name="DrillThroughFilter"><![CDATA[]]></property>
      <property name="DrillThroughFrom"><![CDATA[]]></property>
      <property name="DrillThroughJoins"><![CDATA[]]></property>
      <CustomProperties>
        <Property name="ID" datatype="8"><![CDATA[7cb94f80-41a7-45d8-a928-a9087f1bfb2a]]></Property>
        <Property name="ObjectKey" datatype="8"><![CDATA[798bcb1c-423f-40ee-a746-0125eae93c0c]]></Property>
      </CustomProperties>
      <DataSources>
        <DataSource method="Add" name="dv" ClassType="6" SubClassType="0">
          <CustomProperties>
            <Property name="ID" datatype="8"><![CDATA[af4c64e8-2b41-4fab-a1fa-acd52b27625e]]></Property>
          </CustomProperties>
        </DataSource>
      </DataSources>
      <Aggregations />
    </Partition>
  </Partitions>
</Cube>